{"path":"%D0%A0%D1%8F%D0%B1%D0%B8%D0%BD%D0%B0%20%D0%BE%D0%B1%D1%8B%D0%BA%D0%BD%D0%BE%D0%B2%D0%B5%D0%BD%D0%BD%D0%B0%D1%8F%20-%20Sorbus%20aucuparia","deepCounters":{"total":54,"images":54,"files":54},"counters":{"total":54,"images":54,"files":54},"thumb":{"path":"thumbs\/0DSC00211.webp","width":512,"height":410},"thumbCaption":"<h3>Рябина обыкновенная - Sorbus aucuparia<\/h3>","album":{"description":"<br\/>\nPlant anatomy, Hybrids, Pests and Diseases, Carnivorous, Myco-Heterotrophic, Parasitic, Albinos, Fungi, Succulents, Cactuses, Aquatic, Nut-fruited, Tuberous, Ferns, Mosses, Bulbs, Mutants, Witches' brooms, Fairy rings, Prolific petals, Bad luck, Good luck, Colors, Burls, Mycelium, Molds, Journeys.<br\/><br\/>\nTry also other sites: <br\/>\n    <a href=\"https:\/\/herbarium.info\">Herbarium.INFO<\/a>&nbsp;\u2022&nbsp;\n    <a href=\"https:\/\/herbarium.info\/plantarium.info\">Plantarium.INFO<\/a>&nbsp;\u2022&nbsp;\n    <a href=\"https:\/\/fungarium.info\">Fungarium.INFO<\/a>&nbsp;\u2022&nbsp;\n    <a href=\"https:\/\/herbarium.info\/lichenarium.info\">Lichenarium.INFO<\/a>&nbsp;\u2022&nbsp;\n    <a href=\"https:\/\/herbarium.info\/algaerium.info\">Algaerium.INFO<\/a>","title":"Plantarium.INFO"},"objects":[{"image":{"path":"slides\/0DSC00211.webp","width":2000,"height":1500},"thumb":{"path":"thumbs\/0DSC00211.webp","width":512,"height":410},"thumbCaption":"<span class=\"nr\">1<\/span><div class=\"title\">0DSC00211<\/div>","photodata":"<b>Original Date<\/b> <i>8\/15\/17, 5:05\u202FPM<\/i> &middot; <b>Make<\/b> <i>SONY<\/i> &middot; <b>Camera<\/b> <i>DSC-HX90<\/i> &middot; <b>Lens<\/b> <i>4.1-123mm f\/3.5-6.4<\/i> &middot; <b>Focal Length (35mm)<\/b> <i>24mm<\/i> &middot; <b>Metering Mode<\/b> <i>Multi-segment<\/i> &middot; <b>ISO Equivalent<\/b> <i>80<\/i> &middot; <b>Exposure Time<\/b> <i>1\/400s<\/i> &middot; <b>Aperture<\/b> <i>ƒ\/3.5<\/i> &middot; <b>Exposure bias<\/b> <i>0 EV<\/i> &middot; <b>Exposure Program<\/b> <i>Manual control<\/i> &middot; <b>White balance<\/b> <i>Manual white balance<\/i> &middot; <b>Flash<\/b> <i>Flash did not fire<\/i> &middot; <b>Resolution<\/b> <i>4896 x 3672<\/i>","dates":{"added":1505074921,"dateTaken":1502805946},"fileDate":"2017-08-15T17:05:46.0Z","path":"0DSC00211.webp","imageCaption":"<div class=\"title\">0DSC00211<\/div>","fileSize":1949241,"name":"0DSC00211.webp","comment":"                               ","category":"image","camera":{"aperture":3.5,"exposureTime":"1\/400s","originalDate":"2017-08-15T17:05:46.0Z","cameraModel":"DSC-HX90","focalLength35mm":"24mm","resolution":"4896 x 3672","cameraMake":"SONY","isoEquivalent":80,"flash":"Flash did not fire","focalLength":"4mm"}},{"image":{"path":"slides\/DSC00210.webp","width":2000,"height":1500},"thumb":{"path":"thumbs\/DSC00210.webp","width":512,"height":410},"thumbCaption":"<span class=\"nr\">2<\/span><div class=\"title\">DSC00210<\/div>","photodata":"<b>Original Date<\/b> <i>8\/15\/17, 5:05\u202FPM<\/i> &middot; <b>Make<\/b> <i>SONY<\/i> &middot; <b>Camera<\/b> <i>DSC-HX90<\/i> &middot; <b>Lens<\/b> <i>4.1-123mm f\/3.5-6.4<\/i> &middot; <b>Focal Length (35mm)<\/b> <i>24mm<\/i> &middot; <b>Metering Mode<\/b> <i>Multi-segment<\/i> &middot; <b>ISO Equivalent<\/b> <i>80<\/i> &middot; <b>Exposure Time<\/b> <i>1\/400s<\/i> &middot; <b>Aperture<\/b> <i>ƒ\/3.5<\/i> &middot; <b>Exposure bias<\/b> <i>0 EV<\/i> &middot; <b>Exposure Program<\/b> <i>Manual control<\/i> &middot; <b>White balance<\/b> <i>Manual white balance<\/i> &middot; <b>Flash<\/b> <i>Flash did not fire<\/i> &middot; <b>Resolution<\/b> <i>4896 x 3672<\/i>","dates":{"added":1505074921,"dateTaken":1502805933},"fileDate":"2017-08-15T17:05:32.0Z","path":"DSC00210.webp","imageCaption":"<div class=\"title\">DSC00210<\/div>","fileSize":2386262,"name":"DSC00210.webp","comment":"                               ","category":"image","camera":{"aperture":3.5,"exposureTime":"1\/400s","originalDate":"2017-08-15T17:05:33.0Z","cameraModel":"DSC-HX90","focalLength35mm":"24mm","resolution":"4896 x 3672","cameraMake":"SONY","isoEquivalent":80,"flash":"Flash did not fire","focalLength":"4mm"}},{"image":{"path":"slides\/DSC00211.webp","width":2000,"height":1500},"thumb":{"path":"thumbs\/DSC00211.webp","width":512,"height":410},"thumbCaption":"<span class=\"nr\">3<\/span><div class=\"title\">DSC00211<\/div>","photodata":"<b>Original Date<\/b> <i>8\/15\/17, 5:05\u202FPM<\/i> &middot; <b>Make<\/b> <i>SONY<\/i> &middot; <b>Camera<\/b> <i>DSC-HX90<\/i> &middot; <b>Lens<\/b> <i>4.1-123mm f\/3.5-6.4<\/i> &middot; <b>Focal Length (35mm)<\/b> <i>24mm<\/i> &middot; <b>Metering Mode<\/b> <i>Multi-segment<\/i> &middot; <b>ISO Equivalent<\/b> <i>80<\/i> &middot; <b>Exposure Time<\/b> <i>1\/400s<\/i> &middot; <b>Aperture<\/b> <i>ƒ\/3.5<\/i> &middot; <b>Exposure bias<\/b> <i>0 EV<\/i> &middot; <b>Exposure Program<\/b> <i>Manual control<\/i> &middot; <b>White balance<\/b> <i>Manual white balance<\/i> &middot; <b>Flash<\/b> <i>Flash did not fire<\/i> &middot; <b>Resolution<\/b> <i>4896 x 3672<\/i>","dates":{"added":1507405994,"dateTaken":1502805946},"fileDate":"2017-08-15T17:05:46.0Z","path":"DSC00211.webp","imageCaption":"<div class=\"title\">DSC00211<\/div>","fileSize":1949241,"name":"DSC00211.webp","comment":"                               ","category":"image","camera":{"aperture":3.5,"exposureTime":"1\/400s","originalDate":"2017-08-15T17:05:46.0Z","cameraModel":"DSC-HX90","focalLength35mm":"24mm","resolution":"4896 x 3672","cameraMake":"SONY","isoEquivalent":80,"flash":"Flash did not fire","focalLength":"4mm"}},{"image":{"path":"slides\/DSC00212.webp","width":2000,"height":1500},"thumb":{"path":"thumbs\/DSC00212.webp","width":512,"height":410},"thumbCaption":"<span class=\"nr\">4<\/span><div class=\"title\">DSC00212<\/div>","photodata":"<b>Original Date<\/b> <i>8\/15\/17, 5:06\u202FPM<\/i> &middot; <b>Make<\/b> <i>SONY<\/i> &middot; <b>Camera<\/b> <i>DSC-HX90<\/i> &middot; <b>Lens<\/b> <i>4.1-123mm f\/3.5-6.4<\/i> &middot; <b>Focal Length (35mm)<\/b> <i>24mm<\/i> &middot; <b>Metering Mode<\/b> <i>Multi-segment<\/i> &middot; <b>ISO Equivalent<\/b> <i>80<\/i> &middot; <b>Exposure Time<\/b> <i>1\/640s<\/i> &middot; <b>Aperture<\/b> <i>ƒ\/3.5<\/i> &middot; <b>Exposure bias<\/b> <i>0 EV<\/i> &middot; <b>Exposure Program<\/b> <i>Manual control<\/i> &middot; <b>White balance<\/b> <i>Manual white balance<\/i> &middot; <b>Flash<\/b> <i>Flash did not fire<\/i> &middot; <b>Resolution<\/b> <i>4896 x 3672<\/i>","dates":{"added":1505074921,"dateTaken":1502805967},"fileDate":"2017-08-15T17:06:06.0Z","path":"DSC00212.webp","imageCaption":"<div class=\"title\">DSC00212<\/div>","fileSize":2123542,"name":"DSC00212.webp","comment":"                               ","category":"image","camera":{"aperture":3.5,"exposureTime":"1\/640s","originalDate":"2017-08-15T17:06:07.0Z","cameraModel":"DSC-HX90","focalLength35mm":"24mm","resolution":"4896 x 3672","cameraMake":"SONY","isoEquivalent":80,"flash":"Flash did not fire","focalLength":"4mm"}},{"image":{"path":"slides\/DSC00213.webp","width":2000,"height":1500},"thumb":{"path":"thumbs\/DSC00213.webp","width":512,"height":410},"thumbCaption":"<span class=\"nr\">5<\/span><div class=\"title\">DSC00213<\/div>","photodata":"<b>Original Date<\/b> <i>8\/15\/17, 5:06\u202FPM<\/i> &middot; <b>Make<\/b> <i>SONY<\/i> &middot; <b>Camera<\/b> <i>DSC-HX90<\/i> &middot; <b>Lens<\/b> <i>4.1-123mm f\/3.5-6.4<\/i> &middot; <b>Focal Length (35mm)<\/b> <i>24mm<\/i> &middot; <b>Metering Mode<\/b> <i>Multi-segment<\/i> &middot; <b>ISO Equivalent<\/b> <i>80<\/i> &middot; <b>Exposure Time<\/b> <i>1\/500s<\/i> &middot; <b>Aperture<\/b> <i>ƒ\/3.5<\/i> &middot; <b>Exposure bias<\/b> <i>0 EV<\/i> &middot; <b>Exposure Program<\/b> <i>Manual control<\/i> &middot; <b>White balance<\/b> <i>Manual white balance<\/i> &middot; <b>Flash<\/b> <i>Flash did not fire<\/i> &middot; <b>Resolution<\/b> <i>4896 x 3672<\/i>","dates":{"added":1505074921,"dateTaken":1502805988},"fileDate":"2017-08-15T17:06:28.0Z","path":"DSC00213.webp","imageCaption":"<div class=\"title\">DSC00213<\/div>","fileSize":2702267,"name":"DSC00213.webp","comment":"                               ","category":"image","camera":{"aperture":3.5,"exposureTime":"1\/500s","originalDate":"2017-08-15T17:06:28.0Z","cameraModel":"DSC-HX90","focalLength35mm":"24mm","resolution":"4896 x 3672","cameraMake":"SONY","isoEquivalent":80,"flash":"Flash did not fire","focalLength":"4mm"}},{"image":{"path":"slides\/DSC00490.webp","width":1024,"height":768},"thumb":{"path":"thumbs\/DSC00490.webp","width":512,"height":410},"thumbCaption":"<span class=\"nr\">6<\/span><div class=\"title\">DSC00490<\/div>","photodata":"<b>Original Date<\/b> <i>8\/21\/09, 6:40\u202FPM<\/i> &middot; <b>Make<\/b> <i>SONY<\/i> &middot; <b>Camera<\/b> <i>DSC-T30<\/i> &middot; <b>Focal Length (35mm)<\/b> <i>38mm<\/i> &middot; <b>Metering Mode<\/b> <i>Multi-segment<\/i> &middot; <b>ISO Equivalent<\/b> <i>125<\/i> &middot; <b>Exposure Time<\/b> <i>1\/40s<\/i> &middot; <b>Aperture<\/b> <i>ƒ\/3.5<\/i> &middot; <b>Exposure bias<\/b> <i>0 EV<\/i> &middot; <b>Exposure Program<\/b> <i>Program normal<\/i> &middot; <b>White balance<\/b> <i>Auto white balance<\/i> &middot; <b>Flash<\/b> <i>Flash did not fire<\/i> &middot; <b>Resolution<\/b> <i>2048 x 1536<\/i>","dates":{"added":1505074921,"dateTaken":1250869236},"fileDate":"2009-08-21T19:40:38.0Z","path":"DSC00490.webp","imageCaption":"<div class=\"title\">DSC00490<\/div>","fileSize":1072267,"name":"DSC00490.webp","comment":"                               ","category":"image","camera":{"aperture":3.5,"exposureTime":"1\/40s","originalDate":"2009-08-21T18:40:36.0Z","cameraModel":"DSC-T30","focalLength35mm":"38mm","resolution":"2048 x 1536","cameraMake":"SONY","isoEquivalent":125,"flash":"Flash did not fire","focalLength":"6mm"}},{"image":{"path":"slides\/DSC00499.webp","width":1024,"height":768},"thumb":{"path":"thumbs\/DSC00499.webp","width":512,"height":410},"thumbCaption":"<span class=\"nr\">7<\/span><div class=\"title\">DSC00499<\/div>","photodata":"<b>Original Date<\/b> <i>8\/21\/09, 6:46\u202FPM<\/i> &middot; <b>Make<\/b> <i>SONY<\/i> &middot; <b>Camera<\/b> <i>DSC-T30<\/i> &middot; <b>Focal Length (35mm)<\/b> <i>38mm<\/i> &middot; <b>Metering Mode<\/b> <i>Multi-segment<\/i> &middot; <b>ISO Equivalent<\/b> <i>160<\/i> &middot; <b>Exposure Time<\/b> <i>1\/40s<\/i> &middot; <b>Aperture<\/b> <i>ƒ\/3.5<\/i> &middot; <b>Exposure bias<\/b> <i>0 EV<\/i> &middot; <b>Exposure Program<\/b> <i>Program normal<\/i> &middot; <b>White balance<\/b> <i>Auto white balance<\/i> &middot; <b>Flash<\/b> <i>Flash did not fire<\/i> &middot; <b>Resolution<\/b> <i>2048 x 1536<\/i>","dates":{"added":1505074921,"dateTaken":1250869592},"fileDate":"2009-08-21T19:46:34.0Z","path":"DSC00499.webp","imageCaption":"<div class=\"title\">DSC00499<\/div>","fileSize":540081,"name":"DSC00499.webp","comment":"                               ","category":"image","camera":{"aperture":3.5,"exposureTime":"1\/40s","originalDate":"2009-08-21T18:46:32.0Z","cameraModel":"DSC-T30","focalLength35mm":"38mm","resolution":"2048 x 1536","cameraMake":"SONY","isoEquivalent":160,"flash":"Flash did not fire","focalLength":"6mm"}},{"image":{"path":"slides\/DSC00682.webp","width":1024,"height":768},"thumb":{"path":"thumbs\/DSC00682.webp","width":512,"height":410},"thumbCaption":"<span class=\"nr\">8<\/span><div class=\"title\">DSC00682<\/div>","photodata":"<b>Original Date<\/b> <i>5\/24\/12, 2:03\u202FPM<\/i> &middot; <b>Make<\/b> <i>SONY<\/i> &middot; <b>Camera<\/b> <i>DSC-T30<\/i> &middot; <b>Focal Length (35mm)<\/b> <i>38mm<\/i> &middot; <b>Metering Mode<\/b> <i>Multi-segment<\/i> &middot; <b>ISO Equivalent<\/b> <i>125<\/i> &middot; <b>Exposure Time<\/b> <i>1\/250s<\/i> &middot; <b>Aperture<\/b> <i>ƒ\/5.6<\/i> &middot; <b>Exposure bias<\/b> <i>0 EV<\/i> &middot; <b>Exposure Program<\/b> <i>Program normal<\/i> &middot; <b>White balance<\/b> <i>Auto white balance<\/i> &middot; <b>Flash<\/b> <i>Flash did not fire<\/i> &middot; <b>Resolution<\/b> <i>2048 x 1536<\/i>","dates":{"added":1505074921,"dateTaken":1337857424},"fileDate":"2014-03-15T20:36:44.0Z","path":"DSC00682.webp","imageCaption":"<div class=\"title\">DSC00682<\/div>","fileSize":773572,"name":"DSC00682.webp","comment":"                               ","category":"image","camera":{"aperture":5.6,"exposureTime":"1\/250s","originalDate":"2012-05-24T14:03:44.0Z","cameraModel":"DSC-T30","focalLength35mm":"38mm","resolution":"2048 x 1536","cameraMake":"SONY","isoEquivalent":125,"flash":"Flash did not fire","focalLength":"6mm"}},{"image":{"path":"slides\/DSC00683.webp","width":1024,"height":768},"thumb":{"path":"thumbs\/DSC00683.webp","width":512,"height":410},"thumbCaption":"<span class=\"nr\">9<\/span><div class=\"title\">DSC00683<\/div>","photodata":"<b>Original Date<\/b> <i>5\/24\/12, 2:03\u202FPM<\/i> &middot; <b>Make<\/b> <i>SONY<\/i> &middot; <b>Camera<\/b> <i>DSC-T30<\/i> &middot; <b>Focal Length (35mm)<\/b> <i>38mm<\/i> &middot; <b>Metering Mode<\/b> <i>Multi-segment<\/i> &middot; <b>ISO Equivalent<\/b> <i>125<\/i> &middot; <b>Exposure Time<\/b> <i>1\/400s<\/i> &middot; <b>Aperture<\/b> <i>ƒ\/5.6<\/i> &middot; <b>Exposure bias<\/b> <i>0 EV<\/i> &middot; <b>Exposure Program<\/b> <i>Program normal<\/i> &middot; <b>White balance<\/b> <i>Auto white balance<\/i> &middot; <b>Flash<\/b> <i>Flash did not fire<\/i> &middot; <b>Resolution<\/b> <i>2048 x 1536<\/i>","dates":{"added":1505074921,"dateTaken":1337857431},"fileDate":"2014-03-15T20:36:44.0Z","path":"DSC00683.webp","imageCaption":"<div class=\"title\">DSC00683<\/div>","fileSize":651296,"name":"DSC00683.webp","comment":"                               ","category":"image","camera":{"aperture":5.6,"exposureTime":"1\/400s","originalDate":"2012-05-24T14:03:51.0Z","cameraModel":"DSC-T30","focalLength35mm":"38mm","resolution":"2048 x 1536","cameraMake":"SONY","isoEquivalent":125,"flash":"Flash did not fire","focalLength":"6mm"}},{"image":{"path":"slides\/DSC00859.webp","width":1024,"height":768},"thumb":{"path":"thumbs\/DSC00859.webp","width":512,"height":410},"thumbCaption":"<span class=\"nr\">10<\/span><div class=\"title\">DSC00859<\/div>","photodata":"<b>Original Date<\/b> <i>5\/30\/12, 7:12\u202FPM<\/i> &middot; <b>Make<\/b> <i>SONY<\/i> &middot; <b>Camera<\/b> <i>DSC-T30<\/i> &middot; <b>Focal Length (35mm)<\/b> <i>38mm<\/i> &middot; <b>Metering Mode<\/b> <i>Multi-segment<\/i> &middot; <b>ISO Equivalent<\/b> <i>125<\/i> &middot; <b>Exposure Time<\/b> <i>1\/125s<\/i> &middot; <b>Aperture<\/b> <i>ƒ\/5.6<\/i> &middot; <b>Exposure bias<\/b> <i>0 EV<\/i> &middot; <b>Exposure Program<\/b> <i>Program normal<\/i> &middot; <b>White balance<\/b> <i>Auto white balance<\/i> &middot; <b>Flash<\/b> <i>Flash did not fire<\/i> &middot; <b>Resolution<\/b> <i>2048 x 1536<\/i>","dates":{"added":1505074921,"dateTaken":1338394341},"fileDate":"2014-03-15T20:36:44.0Z","path":"DSC00859.webp","imageCaption":"<div class=\"title\">DSC00859<\/div>","fileSize":737834,"name":"DSC00859.webp","comment":"                               ","category":"image","camera":{"aperture":5.6,"exposureTime":"1\/125s","originalDate":"2012-05-30T19:12:21.0Z","cameraModel":"DSC-T30","focalLength35mm":"38mm","resolution":"2048 x 1536","cameraMake":"SONY","isoEquivalent":125,"flash":"Flash did not fire","focalLength":"6mm"}},{"image":{"path":"slides\/DSC00860.webp","width":1024,"height":768},"thumb":{"path":"thumbs\/DSC00860.webp","width":512,"height":410},"thumbCaption":"<span class=\"nr\">11<\/span><div class=\"title\">DSC00860<\/div>","photodata":"<b>Original Date<\/b> <i>5\/30\/12, 7:12\u202FPM<\/i> &middot; <b>Make<\/b> <i>SONY<\/i> &middot; <b>Camera<\/b> <i>DSC-T30<\/i> &middot; <b>Focal Length (35mm)<\/b> <i>38mm<\/i> &middot; <b>Metering Mode<\/b> <i>Multi-segment<\/i> &middot; <b>ISO Equivalent<\/b> <i>125<\/i> &middot; <b>Exposure Time<\/b> <i>1\/320s<\/i> &middot; <b>Aperture<\/b> <i>ƒ\/5.6<\/i> &middot; <b>Exposure bias<\/b> <i>0 EV<\/i> &middot; <b>Exposure Program<\/b> <i>Program normal<\/i> &middot; <b>White balance<\/b> <i>Auto white balance<\/i> &middot; <b>Flash<\/b> <i>Flash did not fire<\/i> &middot; <b>Resolution<\/b> <i>2048 x 1536<\/i>","dates":{"added":1505074921,"dateTaken":1338394376},"fileDate":"2014-03-15T20:36:44.0Z","path":"DSC00860.webp","imageCaption":"<div class=\"title\">DSC00860<\/div>","fileSize":650469,"name":"DSC00860.webp","comment":"                               ","category":"image","camera":{"aperture":5.6,"exposureTime":"1\/320s","originalDate":"2012-05-30T19:12:56.0Z","cameraModel":"DSC-T30","focalLength35mm":"38mm","resolution":"2048 x 1536","cameraMake":"SONY","isoEquivalent":125,"flash":"Flash did not fire","focalLength":"6mm"}},{"image":{"path":"slides\/DSC00863.webp","width":1024,"height":768},"thumb":{"path":"thumbs\/DSC00863.webp","width":512,"height":410},"thumbCaption":"<span class=\"nr\">12<\/span><div class=\"title\">DSC00863<\/div>","photodata":"<b>Original Date<\/b> <i>5\/30\/12, 7:14\u202FPM<\/i> &middot; <b>Make<\/b> <i>SONY<\/i> &middot; <b>Camera<\/b> <i>DSC-T30<\/i> &middot; <b>Focal Length (35mm)<\/b> <i>38mm<\/i> &middot; <b>Metering Mode<\/b> <i>Multi-segment<\/i> &middot; <b>ISO Equivalent<\/b> <i>125<\/i> &middot; <b>Exposure Time<\/b> <i>1\/200s<\/i> &middot; <b>Aperture<\/b> <i>ƒ\/5.6<\/i> &middot; <b>Exposure bias<\/b> <i>0 EV<\/i> &middot; <b>Exposure Program<\/b> <i>Program normal<\/i> &middot; <b>White balance<\/b> <i>Auto white balance<\/i> &middot; <b>Flash<\/b> <i>Flash did not fire<\/i> &middot; <b>Resolution<\/b> <i>2048 x 1536<\/i>","dates":{"added":1505074921,"dateTaken":1338394464},"fileDate":"2014-03-15T20:36:44.0Z","path":"DSC00863.webp","imageCaption":"<div class=\"title\">DSC00863<\/div>","fileSize":1122259,"name":"DSC00863.webp","comment":"                               ","category":"image","camera":{"aperture":5.6,"exposureTime":"1\/200s","originalDate":"2012-05-30T19:14:24.0Z","cameraModel":"DSC-T30","focalLength35mm":"38mm","resolution":"2048 x 1536","cameraMake":"SONY","isoEquivalent":125,"flash":"Flash did not fire","focalLength":"6mm"}},{"image":{"path":"slides\/DSC00911.webp","width":768,"height":1024},"thumb":{"path":"thumbs\/DSC00911.webp","width":512,"height":410},"thumbCaption":"<span class=\"nr\">13<\/span><div class=\"title\">DSC00911<\/div>","photodata":"<b>Original Date<\/b> <i>5\/30\/12, 7:31\u202FPM<\/i> &middot; <b>Make<\/b> <i>SONY<\/i> &middot; <b>Camera<\/b> <i>DSC-T30<\/i> &middot; <b>Focal Length (35mm)<\/b> <i>38mm<\/i> &middot; <b>Metering Mode<\/b> <i>Multi-segment<\/i> &middot; <b>ISO Equivalent<\/b> <i>320<\/i> &middot; <b>Exposure Time<\/b> <i>1\/30s<\/i> &middot; <b>Aperture<\/b> <i>ƒ\/3.5<\/i> &middot; <b>Exposure bias<\/b> <i>0 EV<\/i> &middot; <b>Exposure Program<\/b> <i>Program normal<\/i> &middot; <b>White balance<\/b> <i>Auto white balance<\/i> &middot; <b>Flash<\/b> <i>Flash did not fire<\/i> &middot; <b>Resolution<\/b> <i>1536 x 2048<\/i>","dates":{"added":1505074921,"dateTaken":1338395462},"fileDate":"2014-03-15T20:36:44.0Z","path":"DSC00911.webp","imageCaption":"<div class=\"title\">DSC00911<\/div>","fileSize":841802,"name":"DSC00911.webp","comment":"                               ","category":"image","camera":{"aperture":3.5,"exposureTime":"1\/30s","originalDate":"2012-05-30T19:31:02.0Z","cameraModel":"DSC-T30","focalLength35mm":"38mm","resolution":"1536 x 2048","cameraMake":"SONY","isoEquivalent":320,"flash":"Flash did not fire","focalLength":"6mm"}},{"image":{"path":"slides\/DSC00992.webp","width":1024,"height":768},"thumb":{"path":"thumbs\/DSC00992.webp","width":512,"height":410},"thumbCaption":"<span class=\"nr\">14<\/span><div class=\"title\">DSC00992<\/div>","photodata":"<b>Original Date<\/b> <i>6\/6\/12, 2:04\u202FPM<\/i> &middot; <b>Make<\/b> <i>SONY<\/i> &middot; <b>Camera<\/b> <i>DSC-T30<\/i> &middot; <b>Focal Length (35mm)<\/b> <i>38mm<\/i> &middot; <b>Metering Mode<\/b> <i>Multi-segment<\/i> &middot; <b>ISO Equivalent<\/b> <i>125<\/i> &middot; <b>Exposure Time<\/b> <i>1\/160s<\/i> &middot; <b>Aperture<\/b> <i>ƒ\/5.6<\/i> &middot; <b>Exposure bias<\/b> <i>0 EV<\/i> &middot; <b>Exposure Program<\/b> <i>Program normal<\/i> &middot; <b>White balance<\/b> <i>Auto white balance<\/i> &middot; <b>Flash<\/b> <i>Flash did not fire<\/i> &middot; <b>Resolution<\/b> <i>2048 x 1536<\/i>","dates":{"added":1505074921,"dateTaken":1338980642},"fileDate":"2014-03-15T20:36:44.0Z","path":"DSC00992.webp","imageCaption":"<div class=\"title\">DSC00992<\/div>","fileSize":1035586,"name":"DSC00992.webp","comment":"                               ","category":"image","camera":{"aperture":5.6,"exposureTime":"1\/160s","originalDate":"2012-06-06T14:04:02.0Z","cameraModel":"DSC-T30","focalLength35mm":"38mm","resolution":"2048 x 1536","cameraMake":"SONY","isoEquivalent":125,"flash":"Flash did not fire","focalLength":"6mm"}},{"image":{"path":"slides\/DSC00998.webp","width":1024,"height":768},"thumb":{"path":"thumbs\/DSC00998.webp","width":512,"height":410},"thumbCaption":"<span class=\"nr\">15<\/span><div class=\"title\">DSC00998<\/div>","photodata":"<b>Original Date<\/b> <i>6\/6\/12, 2:39\u202FPM<\/i> &middot; <b>Make<\/b> <i>SONY<\/i> &middot; <b>Camera<\/b> <i>DSC-T30<\/i> &middot; <b>Focal Length (35mm)<\/b> <i>53mm<\/i> &middot; <b>Metering Mode<\/b> <i>Multi-segment<\/i> &middot; <b>ISO Equivalent<\/b> <i>125<\/i> &middot; <b>Exposure Time<\/b> <i>1\/160s<\/i> &middot; <b>Aperture<\/b> <i>ƒ\/5.6<\/i> &middot; <b>Exposure bias<\/b> <i>0 EV<\/i> &middot; <b>Exposure Program<\/b> <i>Program normal<\/i> &middot; <b>White balance<\/b> <i>Auto white balance<\/i> &middot; <b>Flash<\/b> <i>Flash did not fire<\/i> &middot; <b>Resolution<\/b> <i>2048 x 1536<\/i>","dates":{"added":1505074921,"dateTaken":1338982742},"fileDate":"2014-03-15T20:36:44.0Z","path":"DSC00998.webp","imageCaption":"<div class=\"title\">DSC00998<\/div>","fileSize":1054361,"name":"DSC00998.webp","comment":"                               ","category":"image","camera":{"aperture":5.6,"exposureTime":"1\/160s","originalDate":"2012-06-06T14:39:02.0Z","cameraModel":"DSC-T30","focalLength35mm":"53mm","resolution":"2048 x 1536","cameraMake":"SONY","isoEquivalent":125,"flash":"Flash did not fire","focalLength":"9mm"}},{"image":{"path":"slides\/DSC01974.webp","width":1024,"height":768},"thumb":{"path":"thumbs\/DSC01974.webp","width":512,"height":410},"thumbCaption":"<span class=\"nr\">16<\/span><div class=\"title\">DSC01974<\/div>","photodata":"<b>Original Date<\/b> <i>5\/4\/10, 2:44\u202FPM<\/i> &middot; <b>Make<\/b> <i>SONY<\/i> &middot; <b>Camera<\/b> <i>DSC-T30<\/i> &middot; <b>Focal Length (35mm)<\/b> <i>38mm<\/i> &middot; <b>Metering Mode<\/b> <i>Multi-segment<\/i> &middot; <b>ISO Equivalent<\/b> <i>125<\/i> &middot; <b>Exposure Time<\/b> <i>1\/125s<\/i> &middot; <b>Aperture<\/b> <i>ƒ\/5.6<\/i> &middot; <b>Exposure bias<\/b> <i>0 EV<\/i> &middot; <b>Exposure Program<\/b> <i>Program normal<\/i> &middot; <b>White balance<\/b> <i>Auto white balance<\/i> &middot; <b>Flash<\/b> <i>Flash did not fire<\/i> &middot; <b>Resolution<\/b> <i>2048 x 1536<\/i>","dates":{"added":1505074921,"dateTaken":1272973468},"fileDate":"2014-03-15T20:36:44.0Z","path":"DSC01974.webp","imageCaption":"<div class=\"title\">DSC01974<\/div>","fileSize":422012,"name":"DSC01974.webp","comment":"                               ","category":"image","camera":{"aperture":5.6,"exposureTime":"1\/125s","originalDate":"2010-05-04T14:44:28.0Z","cameraModel":"DSC-T30","focalLength35mm":"38mm","resolution":"2048 x 1536","cameraMake":"SONY","isoEquivalent":125,"flash":"Flash did not fire","focalLength":"6mm"}},{"image":{"path":"slides\/DSC02030.webp","width":1024,"height":768},"thumb":{"path":"thumbs\/DSC02030.webp","width":512,"height":410},"thumbCaption":"<span class=\"nr\">17<\/span><div class=\"title\">DSC02030<\/div>","photodata":"<b>Original Date<\/b> <i>5\/7\/10, 11:31\u202FAM<\/i> &middot; <b>Make<\/b> <i>SONY<\/i> &middot; <b>Camera<\/b> <i>DSC-T30<\/i> &middot; <b>Focal Length (35mm)<\/b> <i>38mm<\/i> &middot; <b>Metering Mode<\/b> <i>Multi-segment<\/i> &middot; <b>ISO Equivalent<\/b> <i>125<\/i> &middot; <b>Exposure Time<\/b> <i>1\/125s<\/i> &middot; <b>Aperture<\/b> <i>ƒ\/3.5<\/i> &middot; <b>Exposure bias<\/b> <i>0 EV<\/i> &middot; <b>Exposure Program<\/b> <i>Program normal<\/i> &middot; <b>White balance<\/b> <i>Auto white balance<\/i> &middot; <b>Flash<\/b> <i>Flash did not fire<\/i> &middot; <b>Resolution<\/b> <i>2048 x 1536<\/i>","dates":{"added":1505074921,"dateTaken":1273221085},"fileDate":"2014-03-15T20:36:46.0Z","path":"DSC02030.webp","imageCaption":"<div class=\"title\">DSC02030<\/div>","fileSize":387638,"name":"DSC02030.webp","comment":"                               ","category":"image","camera":{"aperture":3.5,"exposureTime":"1\/125s","originalDate":"2010-05-07T11:31:25.0Z","cameraModel":"DSC-T30","focalLength35mm":"38mm","resolution":"2048 x 1536","cameraMake":"SONY","isoEquivalent":125,"flash":"Flash did not fire","focalLength":"6mm"}},{"image":{"path":"slides\/DSC02109.webp","width":1024,"height":768},"thumb":{"path":"thumbs\/DSC02109.webp","width":512,"height":410},"thumbCaption":"<span class=\"nr\">18<\/span><div class=\"title\">DSC02109<\/div>","photodata":"<b>Original Date<\/b> <i>5\/12\/10, 8:30\u202FAM<\/i> &middot; <b>Make<\/b> <i>SONY<\/i> &middot; <b>Camera<\/b> <i>DSC-T30<\/i> &middot; <b>Focal Length (35mm)<\/b> <i>38mm<\/i> &middot; <b>Metering Mode<\/b> <i>Multi-segment<\/i> &middot; <b>ISO Equivalent<\/b> <i>125<\/i> &middot; <b>Exposure Time<\/b> <i>1\/60s<\/i> &middot; <b>Aperture<\/b> <i>ƒ\/5.6<\/i> &middot; <b>Exposure bias<\/b> <i>0 EV<\/i> &middot; <b>Exposure Program<\/b> <i>Program normal<\/i> &middot; <b>White balance<\/b> <i>Auto white balance<\/i> &middot; <b>Flash<\/b> <i>Flash fired, return detected<\/i> &middot; <b>Resolution<\/b> <i>2048 x 1536<\/i>","dates":{"added":1505074921,"dateTaken":1273642246},"fileDate":"2014-03-15T20:36:46.0Z","path":"DSC02109.webp","imageCaption":"<div class=\"title\">DSC02109<\/div>","fileSize":527161,"name":"DSC02109.webp","comment":"                               ","category":"image","camera":{"aperture":5.6,"exposureTime":"1\/60s","originalDate":"2010-05-12T08:30:46.0Z","cameraModel":"DSC-T30","focalLength35mm":"38mm","resolution":"2048 x 1536","cameraMake":"SONY","isoEquivalent":125,"flash":"Flash fired, return detected","focalLength":"6mm"}},{"image":{"path":"slides\/DSC02110.webp","width":1024,"height":768},"thumb":{"path":"thumbs\/DSC02110.webp","width":512,"height":410},"thumbCaption":"<span class=\"nr\">19<\/span><div class=\"title\">DSC02110<\/div>","photodata":"<b>Original Date<\/b> <i>5\/12\/10, 8:30\u202FAM<\/i> &middot; <b>Make<\/b> <i>SONY<\/i> &middot; <b>Camera<\/b> <i>DSC-T30<\/i> &middot; <b>Focal Length (35mm)<\/b> <i>38mm<\/i> &middot; <b>Metering Mode<\/b> <i>Multi-segment<\/i> &middot; <b>ISO Equivalent<\/b> <i>125<\/i> &middot; <b>Exposure Time<\/b> <i>1\/50s<\/i> &middot; <b>Aperture<\/b> <i>ƒ\/5.6<\/i> &middot; <b>Exposure bias<\/b> <i>0 EV<\/i> &middot; <b>Exposure Program<\/b> <i>Program normal<\/i> &middot; <b>White balance<\/b> <i>Auto white balance<\/i> &middot; <b>Flash<\/b> <i>Flash fired, return detected<\/i> &middot; <b>Resolution<\/b> <i>2048 x 1536<\/i>","dates":{"added":1505074921,"dateTaken":1273642253},"fileDate":"2014-03-15T20:36:46.0Z","path":"DSC02110.webp","imageCaption":"<div class=\"title\">DSC02110<\/div>","fileSize":566561,"name":"DSC02110.webp","comment":"                               ","category":"image","camera":{"aperture":5.6,"exposureTime":"1\/50s","originalDate":"2010-05-12T08:30:53.0Z","cameraModel":"DSC-T30","focalLength35mm":"38mm","resolution":"2048 x 1536","cameraMake":"SONY","isoEquivalent":125,"flash":"Flash fired, return detected","focalLength":"6mm"}},{"image":{"path":"slides\/DSC02347.webp","width":1024,"height":768},"thumb":{"path":"thumbs\/DSC02347.webp","width":512,"height":410},"thumbCaption":"<span class=\"nr\">20<\/span><div class=\"title\">DSC02347<\/div>","photodata":"<b>Original Date<\/b> <i>5\/29\/10, 10:52\u202FAM<\/i> &middot; <b>Make<\/b> <i>SONY<\/i> &middot; <b>Camera<\/b> <i>DSC-T30<\/i> &middot; <b>Focal Length (35mm)<\/b> <i>38mm<\/i> &middot; <b>Metering Mode<\/b> <i>Multi-segment<\/i> &middot; <b>ISO Equivalent<\/b> <i>125<\/i> &middot; <b>Exposure Time<\/b> <i>1\/160s<\/i> &middot; <b>Aperture<\/b> <i>ƒ\/5.6<\/i> &middot; <b>Exposure bias<\/b> <i>0 EV<\/i> &middot; <b>Exposure Program<\/b> <i>Program normal<\/i> &middot; <b>White balance<\/b> <i>Auto white balance<\/i> &middot; <b>Flash<\/b> <i>Flash did not fire<\/i> &middot; <b>Resolution<\/b> <i>2048 x 1536<\/i>","dates":{"added":1505074921,"dateTaken":1275119543},"fileDate":"2014-03-15T20:36:46.0Z","path":"DSC02347.webp","imageCaption":"<div class=\"title\">DSC02347<\/div>","fileSize":643792,"name":"DSC02347.webp","comment":"                               ","category":"image","camera":{"aperture":5.6,"exposureTime":"1\/160s","originalDate":"2010-05-29T10:52:23.0Z","cameraModel":"DSC-T30","focalLength35mm":"38mm","resolution":"2048 x 1536","cameraMake":"SONY","isoEquivalent":125,"flash":"Flash did not fire","focalLength":"6mm"}},{"image":{"path":"slides\/DSC02457.webp","width":2000,"height":1500},"thumb":{"path":"thumbs\/DSC02457.webp","width":512,"height":410},"thumbCaption":"<span class=\"nr\">21<\/span><div class=\"title\">DSC02457<\/div>","photodata":"<b>Original Date<\/b> <i>5\/8\/15, 2:48\u202FPM<\/i> &middot; <b>Make<\/b> <i>SONY<\/i> &middot; <b>Camera<\/b> <i>DSC-HX50<\/i> &middot; <b>Lens<\/b> <i>4.3-129mm f\/3.5-6.3<\/i> &middot; <b>Focal Length<\/b> <i>4.3 mm<\/i> &middot; <b>Metering Mode<\/b> <i>Multi-segment<\/i> &middot; <b>ISO Equivalent<\/b> <i>80<\/i> &middot; <b>Exposure Time<\/b> <i>1\/100s<\/i> &middot; <b>Aperture<\/b> <i>ƒ\/3.5<\/i> &middot; <b>Exposure bias<\/b> <i>0.7 EV<\/i> &middot; <b>Exposure Program<\/b> <i>Program normal<\/i> &middot; <b>White balance<\/b> <i>Auto white balance<\/i> &middot; <b>Flash<\/b> <i>Flash did not fire<\/i> &middot; <b>Resolution<\/b> <i>5184 x 3888<\/i>","dates":{"added":1505074921,"dateTaken":1431085692},"fileDate":"2015-05-08T15:27:38.0Z","path":"DSC02457.webp","imageCaption":"<div class=\"title\">DSC02457<\/div>","fileSize":1430996,"name":"DSC02457.webp","comment":"                               ","category":"image","camera":{"aperture":3.5,"exposureTime":"1\/100s","originalDate":"2015-05-08T14:48:12.0Z","cameraModel":"DSC-HX50","resolution":"5184 x 3888","cameraMake":"SONY","isoEquivalent":80,"flash":"Flash did not fire","focalLength":"4mm"}},{"image":{"path":"slides\/DSC02458.webp","width":2000,"height":1500},"thumb":{"path":"thumbs\/DSC02458.webp","width":512,"height":410},"thumbCaption":"<span class=\"nr\">22<\/span><div class=\"title\">DSC02458<\/div>","photodata":"<b>Original Date<\/b> <i>5\/8\/15, 2:48\u202FPM<\/i> &middot; <b>Make<\/b> <i>SONY<\/i> &middot; <b>Camera<\/b> <i>DSC-HX50<\/i> &middot; <b>Lens<\/b> <i>4.3-129mm f\/3.5-6.3<\/i> &middot; <b>Focal Length<\/b> <i>4.3 mm<\/i> &middot; <b>Metering Mode<\/b> <i>Multi-segment<\/i> &middot; <b>ISO Equivalent<\/b> <i>80<\/i> &middot; <b>Exposure Time<\/b> <i>1\/100s<\/i> &middot; <b>Aperture<\/b> <i>ƒ\/3.5<\/i> &middot; <b>Exposure bias<\/b> <i>0.7 EV<\/i> &middot; <b>Exposure Program<\/b> <i>Program normal<\/i> &middot; <b>White balance<\/b> <i>Auto white balance<\/i> &middot; <b>Flash<\/b> <i>Flash did not fire<\/i> &middot; <b>Resolution<\/b> <i>5184 x 3888<\/i>","dates":{"added":1505074921,"dateTaken":1431085701},"fileDate":"2015-05-08T15:27:40.0Z","path":"DSC02458.webp","imageCaption":"<div class=\"title\">DSC02458<\/div>","fileSize":1485141,"name":"DSC02458.webp","comment":"                               ","category":"image","camera":{"aperture":3.5,"exposureTime":"1\/100s","originalDate":"2015-05-08T14:48:21.0Z","cameraModel":"DSC-HX50","resolution":"5184 x 3888","cameraMake":"SONY","isoEquivalent":80,"flash":"Flash did not fire","focalLength":"4mm"}},{"image":{"path":"slides\/DSC02459.webp","width":2000,"height":1500},"thumb":{"path":"thumbs\/DSC02459.webp","width":512,"height":410},"thumbCaption":"<span class=\"nr\">23<\/span><div class=\"title\">DSC02459<\/div>","photodata":"<b>Original Date<\/b> <i>5\/8\/15, 2:48\u202FPM<\/i> &middot; <b>Make<\/b> <i>SONY<\/i> &middot; <b>Camera<\/b> <i>DSC-HX50<\/i> &middot; <b>Lens<\/b> <i>4.3-129mm f\/3.5-6.3<\/i> &middot; <b>Focal Length<\/b> <i>4.3 mm<\/i> &middot; <b>Metering Mode<\/b> <i>Multi-segment<\/i> &middot; <b>ISO Equivalent<\/b> <i>80<\/i> &middot; <b>Exposure Time<\/b> <i>1\/80s<\/i> &middot; <b>Aperture<\/b> <i>ƒ\/3.5<\/i> &middot; <b>Exposure bias<\/b> <i>0.7 EV<\/i> &middot; <b>Exposure Program<\/b> <i>Program normal<\/i> &middot; <b>White balance<\/b> <i>Auto white balance<\/i> &middot; <b>Flash<\/b> <i>Flash did not fire<\/i> &middot; <b>Resolution<\/b> <i>5184 x 3888<\/i>","dates":{"added":1505074921,"dateTaken":1431085714},"fileDate":"2015-05-08T15:27:40.0Z","path":"DSC02459.webp","imageCaption":"<div class=\"title\">DSC02459<\/div>","fileSize":1418376,"name":"DSC02459.webp","comment":"                               ","category":"image","camera":{"aperture":3.5,"exposureTime":"1\/80s","originalDate":"2015-05-08T14:48:34.0Z","cameraModel":"DSC-HX50","resolution":"5184 x 3888","cameraMake":"SONY","isoEquivalent":80,"flash":"Flash did not fire","focalLength":"4mm"}},{"image":{"path":"slides\/DSC02460.webp","width":2000,"height":1500},"thumb":{"path":"thumbs\/DSC02460.webp","width":512,"height":410},"thumbCaption":"<span class=\"nr\">24<\/span><div class=\"title\">DSC02460<\/div>","photodata":"<b>Original Date<\/b> <i>5\/8\/15, 2:48\u202FPM<\/i> &middot; <b>Make<\/b> <i>SONY<\/i> &middot; <b>Camera<\/b> <i>DSC-HX50<\/i> &middot; <b>Lens<\/b> <i>4.3-129mm f\/3.5-6.3<\/i> &middot; <b>Focal Length<\/b> <i>4.3 mm<\/i> &middot; <b>Metering Mode<\/b> <i>Multi-segment<\/i> &middot; <b>ISO Equivalent<\/b> <i>80<\/i> &middot; <b>Exposure Time<\/b> <i>1\/80s<\/i> &middot; <b>Aperture<\/b> <i>ƒ\/3.5<\/i> &middot; <b>Exposure bias<\/b> <i>0.7 EV<\/i> &middot; <b>Exposure Program<\/b> <i>Program normal<\/i> &middot; <b>White balance<\/b> <i>Auto white balance<\/i> &middot; <b>Flash<\/b> <i>Flash did not fire<\/i> &middot; <b>Resolution<\/b> <i>5184 x 3888<\/i>","dates":{"added":1505074921,"dateTaken":1431085735},"fileDate":"2015-05-08T15:27:42.0Z","path":"DSC02460.webp","imageCaption":"<div class=\"title\">DSC02460<\/div>","fileSize":1412127,"name":"DSC02460.webp","comment":"                               ","category":"image","camera":{"aperture":3.5,"exposureTime":"1\/80s","originalDate":"2015-05-08T14:48:55.0Z","cameraModel":"DSC-HX50","resolution":"5184 x 3888","cameraMake":"SONY","isoEquivalent":80,"flash":"Flash did not fire","focalLength":"4mm"}},{"image":{"path":"slides\/DSC02922.webp","width":1024,"height":768},"thumb":{"path":"thumbs\/DSC02922.webp","width":512,"height":410},"thumbCaption":"<span class=\"nr\">25<\/span><div class=\"title\">DSC02922<\/div>","photodata":"<b>Original Date<\/b> <i>5\/7\/09, 11:46\u202FPM<\/i> &middot; <b>Make<\/b> <i>SONY<\/i> &middot; <b>Camera<\/b> <i>DSC-T30<\/i> &middot; <b>Focal Length (35mm)<\/b> <i>38mm<\/i> &middot; <b>Metering Mode<\/b> <i>Multi-segment<\/i> &middot; <b>ISO Equivalent<\/b> <i>125<\/i> &middot; <b>Exposure Time<\/b> <i>1\/125s<\/i> &middot; <b>Aperture<\/b> <i>ƒ\/5.6<\/i> &middot; <b>Exposure bias<\/b> <i>0 EV<\/i> &middot; <b>Exposure Program<\/b> <i>Program normal<\/i> &middot; <b>White balance<\/b> <i>Auto white balance<\/i> &middot; <b>Flash<\/b> <i>Flash did not fire<\/i> &middot; <b>Resolution<\/b> <i>2048 x 1536<\/i>","dates":{"added":1505074921,"dateTaken":1241729174},"fileDate":"2009-05-08T00:46:16.0Z","path":"DSC02922.webp","imageCaption":"<div class=\"title\">DSC02922<\/div>","fileSize":411878,"name":"DSC02922.webp","comment":"                               ","category":"image","camera":{"aperture":5.6,"exposureTime":"1\/125s","originalDate":"2009-05-07T23:46:14.0Z","cameraModel":"DSC-T30","focalLength35mm":"38mm","resolution":"2048 x 1536","cameraMake":"SONY","isoEquivalent":125,"flash":"Flash did not fire","focalLength":"6mm"}},{"image":{"path":"slides\/DSC03487.webp","width":1024,"height":768},"thumb":{"path":"thumbs\/DSC03487.webp","width":512,"height":410},"thumbCaption":"<span class=\"nr\">26<\/span><div class=\"title\">DSC03487<\/div>","photodata":"<b>Original Date<\/b> <i>8\/15\/12, 12:29\u202FPM<\/i> &middot; <b>Make<\/b> <i>SONY<\/i> &middot; <b>Camera<\/b> <i>DSC-T30<\/i> &middot; <b>Focal Length (35mm)<\/b> <i>38mm<\/i> &middot; <b>Metering Mode<\/b> <i>Multi-segment<\/i> &middot; <b>ISO Equivalent<\/b> <i>125<\/i> &middot; <b>Exposure Time<\/b> <i>1\/125s<\/i> &middot; <b>Aperture<\/b> <i>ƒ\/3.5<\/i> &middot; <b>Exposure bias<\/b> <i>0 EV<\/i> &middot; <b>Exposure Program<\/b> <i>Program normal<\/i> &middot; <b>White balance<\/b> <i>Auto white balance<\/i> &middot; <b>Flash<\/b> <i>Flash did not fire<\/i> &middot; <b>Resolution<\/b> <i>2048 x 1536<\/i>","dates":{"added":1505074921,"dateTaken":1345022992},"fileDate":"2014-03-15T20:36:46.0Z","path":"DSC03487.webp","imageCaption":"<div class=\"title\">DSC03487<\/div>","fileSize":1149946,"name":"DSC03487.webp","comment":"                               ","category":"image","camera":{"aperture":3.5,"exposureTime":"1\/125s","originalDate":"2012-08-15T12:29:52.0Z","cameraModel":"DSC-T30","focalLength35mm":"38mm","resolution":"2048 x 1536","cameraMake":"SONY","isoEquivalent":125,"flash":"Flash did not fire","focalLength":"6mm"}},{"image":{"path":"slides\/DSC03488.webp","width":1024,"height":768},"thumb":{"path":"thumbs\/DSC03488.webp","width":512,"height":410},"thumbCaption":"<span class=\"nr\">27<\/span><div class=\"title\">DSC03488<\/div>","photodata":"<b>Original Date<\/b> <i>8\/15\/12, 12:29\u202FPM<\/i> &middot; <b>Make<\/b> <i>SONY<\/i> &middot; <b>Camera<\/b> <i>DSC-T30<\/i> &middot; <b>Focal Length (35mm)<\/b> <i>58mm<\/i> &middot; <b>Metering Mode<\/b> <i>Multi-segment<\/i> &middot; <b>ISO Equivalent<\/b> <i>125<\/i> &middot; <b>Exposure Time<\/b> <i>1\/125s<\/i> &middot; <b>Aperture<\/b> <i>ƒ\/4<\/i> &middot; <b>Exposure bias<\/b> <i>0 EV<\/i> &middot; <b>Exposure Program<\/b> <i>Program normal<\/i> &middot; <b>White balance<\/b> <i>Auto white balance<\/i> &middot; <b>Flash<\/b> <i>Flash did not fire<\/i> &middot; <b>Resolution<\/b> <i>2048 x 1536<\/i>","dates":{"added":1505074921,"dateTaken":1345022998},"fileDate":"2014-03-15T20:36:46.0Z","path":"DSC03488.webp","imageCaption":"<div class=\"title\">DSC03488<\/div>","fileSize":772855,"name":"DSC03488.webp","comment":"                               ","category":"image","camera":{"aperture":4.0,"exposureTime":"1\/125s","originalDate":"2012-08-15T12:29:58.0Z","cameraModel":"DSC-T30","focalLength35mm":"58mm","resolution":"2048 x 1536","cameraMake":"SONY","isoEquivalent":125,"flash":"Flash did not fire","focalLength":"10mm"}},{"image":{"path":"slides\/DSC03638.webp","width":1024,"height":768},"thumb":{"path":"thumbs\/DSC03638.webp","width":512,"height":410},"thumbCaption":"<span class=\"nr\">28<\/span><div class=\"title\">DSC03638<\/div>","photodata":"<b>Original Date<\/b> <i>8\/29\/12, 7:09\u202FPM<\/i> &middot; <b>Make<\/b> <i>SONY<\/i> &middot; <b>Camera<\/b> <i>DSC-T30<\/i> &middot; <b>Focal Length (35mm)<\/b> <i>38mm<\/i> &middot; <b>Metering Mode<\/b> <i>Multi-segment<\/i> &middot; <b>ISO Equivalent<\/b> <i>125<\/i> &middot; <b>Exposure Time<\/b> <i>1\/160s<\/i> &middot; <b>Aperture<\/b> <i>ƒ\/5.6<\/i> &middot; <b>Exposure bias<\/b> <i>0 EV<\/i> &middot; <b>Exposure Program<\/b> <i>Program normal<\/i> &middot; <b>White balance<\/b> <i>Auto white balance<\/i> &middot; <b>Flash<\/b> <i>Flash did not fire<\/i> &middot; <b>Resolution<\/b> <i>2048 x 1536<\/i>","dates":{"added":1505074921,"dateTaken":1346256541},"fileDate":"2014-03-15T20:36:46.0Z","path":"DSC03638.webp","imageCaption":"<div class=\"title\">DSC03638<\/div>","fileSize":498442,"name":"DSC03638.webp","comment":"                               ","category":"image","camera":{"aperture":5.6,"exposureTime":"1\/160s","originalDate":"2012-08-29T19:09:01.0Z","cameraModel":"DSC-T30","focalLength35mm":"38mm","resolution":"2048 x 1536","cameraMake":"SONY","isoEquivalent":125,"flash":"Flash did not fire","focalLength":"6mm"}},{"image":{"path":"slides\/DSC03639.webp","width":1024,"height":768},"thumb":{"path":"thumbs\/DSC03639.webp","width":512,"height":410},"thumbCaption":"<span class=\"nr\">29<\/span><div class=\"title\">DSC03639<\/div>","photodata":"<b>Original Date<\/b> <i>8\/29\/12, 7:09\u202FPM<\/i> &middot; <b>Make<\/b> <i>SONY<\/i> &middot; <b>Camera<\/b> <i>DSC-T30<\/i> &middot; <b>Focal Length (35mm)<\/b> <i>38mm<\/i> &middot; <b>Metering Mode<\/b> <i>Multi-segment<\/i> &middot; <b>ISO Equivalent<\/b> <i>125<\/i> &middot; <b>Exposure Time<\/b> <i>1\/320s<\/i> &middot; <b>Aperture<\/b> <i>ƒ\/5.6<\/i> &middot; <b>Exposure bias<\/b> <i>0 EV<\/i> &middot; <b>Exposure Program<\/b> <i>Program normal<\/i> &middot; <b>White balance<\/b> <i>Auto white balance<\/i> &middot; <b>Flash<\/b> <i>Flash did not fire<\/i> &middot; <b>Resolution<\/b> <i>2048 x 1536<\/i>","dates":{"added":1505074921,"dateTaken":1346256549},"fileDate":"2014-03-15T20:36:46.0Z","path":"DSC03639.webp","imageCaption":"<div class=\"title\">DSC03639<\/div>","fileSize":361459,"name":"DSC03639.webp","comment":"                               ","category":"image","camera":{"aperture":5.6,"exposureTime":"1\/320s","originalDate":"2012-08-29T19:09:09.0Z","cameraModel":"DSC-T30","focalLength35mm":"38mm","resolution":"2048 x 1536","cameraMake":"SONY","isoEquivalent":125,"flash":"Flash did not fire","focalLength":"6mm"}},{"image":{"path":"slides\/DSC04223.webp","width":768,"height":1024},"thumb":{"path":"thumbs\/DSC04223.webp","width":512,"height":410},"thumbCaption":"<span class=\"nr\">30<\/span><div class=\"title\">DSC04223<\/div>","photodata":"<b>Original Date<\/b> <i>7\/14\/10, 9:24\u202FAM<\/i> &middot; <b>Make<\/b> <i>SONY<\/i> &middot; <b>Camera<\/b> <i>DSC-T30<\/i> &middot; <b>Focal Length (35mm)<\/b> <i>38mm<\/i> &middot; <b>Metering Mode<\/b> <i>Multi-segment<\/i> &middot; <b>ISO Equivalent<\/b> <i>125<\/i> &middot; <b>Exposure Time<\/b> <i>1\/200s<\/i> &middot; <b>Aperture<\/b> <i>ƒ\/5.6<\/i> &middot; <b>Exposure bias<\/b> <i>0 EV<\/i> &middot; <b>Exposure Program<\/b> <i>Program normal<\/i> &middot; <b>White balance<\/b> <i>Auto white balance<\/i> &middot; <b>Flash<\/b> <i>Flash did not fire<\/i> &middot; <b>Resolution<\/b> <i>1536 x 2048<\/i>","dates":{"added":1505074921,"dateTaken":1279088647},"fileDate":"2014-03-15T20:36:46.0Z","path":"DSC04223.webp","imageCaption":"<div class=\"title\">DSC04223<\/div>","fileSize":784634,"name":"DSC04223.webp","comment":"                               ","category":"image","camera":{"aperture":5.6,"exposureTime":"1\/200s","originalDate":"2010-07-14T09:24:07.0Z","cameraModel":"DSC-T30","focalLength35mm":"38mm","resolution":"1536 x 2048","cameraMake":"SONY","isoEquivalent":125,"flash":"Flash did not fire","focalLength":"6mm"}},{"image":{"path":"slides\/DSC04343.webp","width":1024,"height":768},"thumb":{"path":"thumbs\/DSC04343.webp","width":512,"height":410},"thumbCaption":"<span class=\"nr\">31<\/span><div class=\"title\">DSC04343<\/div>","photodata":"<b>Original Date<\/b> <i>8\/11\/10, 6:54\u202FPM<\/i> &middot; <b>Make<\/b> <i>SONY<\/i> &middot; <b>Camera<\/b> <i>DSC-T30<\/i> &middot; <b>Focal Length (35mm)<\/b> <i>38mm<\/i> &middot; <b>Metering Mode<\/b> <i>Multi-segment<\/i> &middot; <b>ISO Equivalent<\/b> <i>320<\/i> &middot; <b>Exposure Time<\/b> <i>1\/40s<\/i> &middot; <b>Aperture<\/b> <i>ƒ\/3.5<\/i> &middot; <b>Exposure bias<\/b> <i>0 EV<\/i> &middot; <b>Exposure Program<\/b> <i>Program normal<\/i> &middot; <b>White balance<\/b> <i>Auto white balance<\/i> &middot; <b>Flash<\/b> <i>Flash did not fire<\/i> &middot; <b>Resolution<\/b> <i>2048 x 1536<\/i>","dates":{"added":1505074921,"dateTaken":1281542084},"fileDate":"2014-03-15T20:36:46.0Z","path":"DSC04343.webp","imageCaption":"<div class=\"title\">DSC04343<\/div>","fileSize":623943,"name":"DSC04343.webp","comment":"                               ","category":"image","camera":{"aperture":3.5,"exposureTime":"1\/40s","originalDate":"2010-08-11T18:54:44.0Z","cameraModel":"DSC-T30","focalLength35mm":"38mm","resolution":"2048 x 1536","cameraMake":"SONY","isoEquivalent":320,"flash":"Flash did not fire","focalLength":"6mm"}},{"image":{"path":"slides\/DSC05205.webp","width":1024,"height":768},"thumb":{"path":"thumbs\/DSC05205.webp","width":512,"height":410},"thumbCaption":"<span class=\"nr\">32<\/span><div class=\"title\">DSC05205<\/div>","photodata":"<b>Original Date<\/b> <i>10\/5\/10, 9:43\u202FAM<\/i> &middot; <b>Make<\/b> <i>SONY<\/i> &middot; <b>Camera<\/b> <i>DSC-T30<\/i> &middot; <b>Focal Length (35mm)<\/b> <i>38mm<\/i> &middot; <b>Metering Mode<\/b> <i>Multi-segment<\/i> &middot; <b>ISO Equivalent<\/b> <i>125<\/i> &middot; <b>Exposure Time<\/b> <i>1\/250s<\/i> &middot; <b>Aperture<\/b> <i>ƒ\/5.6<\/i> &middot; <b>Exposure bias<\/b> <i>0 EV<\/i> &middot; <b>Exposure Program<\/b> <i>Program normal<\/i> &middot; <b>White balance<\/b> <i>Auto white balance<\/i> &middot; <b>Flash<\/b> <i>Flash did not fire<\/i> &middot; <b>Resolution<\/b> <i>2048 x 1536<\/i>","dates":{"added":1505074921,"dateTaken":1286260985},"fileDate":"2014-03-15T20:36:46.0Z","path":"DSC05205.webp","imageCaption":"<div class=\"title\">DSC05205<\/div>","fileSize":1066007,"name":"DSC05205.webp","comment":"                               ","category":"image","camera":{"aperture":5.6,"exposureTime":"1\/250s","originalDate":"2010-10-05T09:43:05.0Z","cameraModel":"DSC-T30","focalLength35mm":"38mm","resolution":"2048 x 1536","cameraMake":"SONY","isoEquivalent":125,"flash":"Flash did not fire","focalLength":"6mm"}},{"image":{"path":"slides\/DSC05206.webp","width":1024,"height":768},"thumb":{"path":"thumbs\/DSC05206.webp","width":512,"height":410},"thumbCaption":"<span class=\"nr\">33<\/span><div class=\"title\">DSC05206<\/div>","photodata":"<b>Original Date<\/b> <i>10\/5\/10, 9:43\u202FAM<\/i> &middot; <b>Make<\/b> <i>SONY<\/i> &middot; <b>Camera<\/b> <i>DSC-T30<\/i> &middot; <b>Focal Length (35mm)<\/b> <i>38mm<\/i> &middot; <b>Metering Mode<\/b> <i>Multi-segment<\/i> &middot; <b>ISO Equivalent<\/b> <i>125<\/i> &middot; <b>Exposure Time<\/b> <i>1\/250s<\/i> &middot; <b>Aperture<\/b> <i>ƒ\/5.6<\/i> &middot; <b>Exposure bias<\/b> <i>0 EV<\/i> &middot; <b>Exposure Program<\/b> <i>Program normal<\/i> &middot; <b>White balance<\/b> <i>Auto white balance<\/i> &middot; <b>Flash<\/b> <i>Flash did not fire<\/i> &middot; <b>Resolution<\/b> <i>2048 x 1536<\/i>","dates":{"added":1505074921,"dateTaken":1286260991},"fileDate":"2014-03-15T20:36:46.0Z","path":"DSC05206.webp","imageCaption":"<div class=\"title\">DSC05206<\/div>","fileSize":614691,"name":"DSC05206.webp","comment":"                               ","category":"image","camera":{"aperture":5.6,"exposureTime":"1\/250s","originalDate":"2010-10-05T09:43:11.0Z","cameraModel":"DSC-T30","focalLength35mm":"38mm","resolution":"2048 x 1536","cameraMake":"SONY","isoEquivalent":125,"flash":"Flash did not fire","focalLength":"6mm"}},{"image":{"path":"slides\/DSC05912.webp","width":2000,"height":1500},"thumb":{"path":"thumbs\/DSC05912.webp","width":512,"height":410},"thumbCaption":"<span class=\"nr\">34<\/span><div class=\"title\">DSC05912<\/div>","photodata":"<b>Original Date<\/b> <i>5\/10\/20, 2:21\u202FPM<\/i> &middot; <b>Make<\/b> <i>SONY<\/i> &middot; <b>Camera<\/b> <i>DSC-HX90V<\/i> &middot; <b>Lens<\/b> <i>4.1-123mm f\/3.5-6.4<\/i> &middot; <b>Focal Length (35mm)<\/b> <i>31mm<\/i> &middot; <b>Metering Mode<\/b> <i>Multi-segment<\/i> &middot; <b>ISO Equivalent<\/b> <i>80<\/i> &middot; <b>Exposure Time<\/b> <i>1\/250s<\/i> &middot; <b>Aperture<\/b> <i>ƒ\/4<\/i> &middot; <b>Exposure bias<\/b> <i>0 EV<\/i> &middot; <b>Exposure Program<\/b> <i>Manual control<\/i> &middot; <b>White balance<\/b> <i>Manual white balance<\/i> &middot; <b>Flash<\/b> <i>Flash did not fire<\/i> &middot; <b>Resolution<\/b> <i>4896 x 3672<\/i>","dates":{"added":1592318088,"dateTaken":1589109683},"fileDate":"2020-05-10T14:21:22.0Z","path":"DSC05912.webp","imageCaption":"<div class=\"title\">DSC05912<\/div>","fileSize":6600210,"name":"DSC05912.webp","comment":"                               ","category":"image","camera":{"aperture":4.0,"exposureTime":"1\/250s","originalDate":"2020-05-10T14:21:23.0Z","cameraModel":"DSC-HX90V","focalLength35mm":"31mm","resolution":"4896 x 3672","cameraMake":"SONY","isoEquivalent":80,"flash":"Flash did not fire","focalLength":"5mm"}},{"image":{"path":"slides\/DSC05913.webp","width":2000,"height":1500},"thumb":{"path":"thumbs\/DSC05913.webp","width":512,"height":410},"thumbCaption":"<span class=\"nr\">35<\/span><div class=\"title\">DSC05913<\/div>","photodata":"<b>Original Date<\/b> <i>5\/10\/20, 2:21\u202FPM<\/i> &middot; <b>Make<\/b> <i>SONY<\/i> &middot; <b>Camera<\/b> <i>DSC-HX90V<\/i> &middot; <b>Lens<\/b> <i>4.1-123mm f\/3.5-6.4<\/i> &middot; <b>Focal Length (35mm)<\/b> <i>31mm<\/i> &middot; <b>Metering Mode<\/b> <i>Multi-segment<\/i> &middot; <b>ISO Equivalent<\/b> <i>80<\/i> &middot; <b>Exposure Time<\/b> <i>1\/250s<\/i> &middot; <b>Aperture<\/b> <i>ƒ\/4<\/i> &middot; <b>Exposure bias<\/b> <i>0 EV<\/i> &middot; <b>Exposure Program<\/b> <i>Manual control<\/i> &middot; <b>White balance<\/b> <i>Manual white balance<\/i> &middot; <b>Flash<\/b> <i>Flash did not fire<\/i> &middot; <b>Resolution<\/b> <i>4896 x 3672<\/i>","dates":{"added":1592318088,"dateTaken":1589109704},"fileDate":"2020-05-10T14:21:44.0Z","path":"DSC05913.webp","imageCaption":"<div class=\"title\">DSC05913<\/div>","fileSize":6494019,"name":"DSC05913.webp","comment":"                               ","category":"image","camera":{"aperture":4.0,"exposureTime":"1\/250s","originalDate":"2020-05-10T14:21:44.0Z","cameraModel":"DSC-HX90V","focalLength35mm":"31mm","resolution":"4896 x 3672","cameraMake":"SONY","isoEquivalent":80,"flash":"Flash did not fire","focalLength":"5mm"}},{"image":{"path":"slides\/DSC05914.webp","width":1500,"height":2000},"thumb":{"path":"thumbs\/DSC05914.webp","width":512,"height":410},"thumbCaption":"<span class=\"nr\">36<\/span><div class=\"title\">DSC05914<\/div>","photodata":"<b>Original Date<\/b> <i>5\/10\/20, 2:21\u202FPM<\/i> &middot; <b>Make<\/b> <i>SONY<\/i> &middot; <b>Camera<\/b> <i>DSC-HX90V<\/i> &middot; <b>Lens<\/b> <i>4.1-123mm f\/3.5-6.4<\/i> &middot; <b>Focal Length (35mm)<\/b> <i>31mm<\/i> &middot; <b>Metering Mode<\/b> <i>Multi-segment<\/i> &middot; <b>ISO Equivalent<\/b> <i>80<\/i> &middot; <b>Exposure Time<\/b> <i>1\/250s<\/i> &middot; <b>Aperture<\/b> <i>ƒ\/4<\/i> &middot; <b>Exposure bias<\/b> <i>0 EV<\/i> &middot; <b>Exposure Program<\/b> <i>Manual control<\/i> &middot; <b>White balance<\/b> <i>Manual white balance<\/i> &middot; <b>Flash<\/b> <i>Flash did not fire<\/i> &middot; <b>Resolution<\/b> <i>4896 x 3672<\/i>","dates":{"added":1592318088,"dateTaken":1589109711},"fileDate":"2020-05-10T14:21:50.0Z","path":"DSC05914.webp","imageCaption":"<div class=\"title\">DSC05914<\/div>","fileSize":6604697,"name":"DSC05914.webp","comment":"                               ","category":"image","camera":{"aperture":4.0,"exposureTime":"1\/250s","originalDate":"2020-05-10T14:21:51.0Z","cameraModel":"DSC-HX90V","focalLength35mm":"31mm","resolution":"4896 x 3672","cameraMake":"SONY","isoEquivalent":80,"flash":"Flash did not fire","focalLength":"5mm"}},{"image":{"path":"slides\/DSC06051.webp","width":1500,"height":2000},"thumb":{"path":"thumbs\/DSC06051.webp","width":512,"height":410},"thumbCaption":"<span class=\"nr\">37<\/span><div class=\"title\">DSC06051<\/div>","photodata":"<b>Original Date<\/b> <i>5\/17\/20, 4:25\u202FPM<\/i> &middot; <b>Make<\/b> <i>SONY<\/i> &middot; <b>Camera<\/b> <i>DSC-HX90V<\/i> &middot; <b>Lens<\/b> <i>4.1-123mm f\/3.5-6.4<\/i> &middot; <b>Focal Length (35mm)<\/b> <i>24mm<\/i> &middot; <b>Metering Mode<\/b> <i>Multi-segment<\/i> &middot; <b>ISO Equivalent<\/b> <i>400<\/i> &middot; <b>Exposure Time<\/b> <i>1\/250s<\/i> &middot; <b>Aperture<\/b> <i>ƒ\/4.5<\/i> &middot; <b>Exposure bias<\/b> <i>0 EV<\/i> &middot; <b>Exposure Program<\/b> <i>Manual control<\/i> &middot; <b>White balance<\/b> <i>Manual white balance<\/i> &middot; <b>Flash<\/b> <i>Flash did not fire<\/i> &middot; <b>Resolution<\/b> <i>4896 x 3672<\/i>","dates":{"added":1592318088,"dateTaken":1589721938},"fileDate":"2020-05-17T16:25:38.0Z","path":"DSC06051.webp","imageCaption":"<div class=\"title\">DSC06051<\/div>","fileSize":8203770,"name":"DSC06051.webp","comment":"                               ","location":"59.422120,28.117928","category":"image","camera":{"aperture":4.5,"exposureTime":"1\/250s","originalDate":"2020-05-17T16:25:38.0Z","cameraModel":"DSC-HX90V","location":{"altitude":"13.7 metres","latitude":"59° 25' 19.63\"","lat":59.42212,"long":28.117928,"longitude":"28° 7' 4.54\""},"focalLength35mm":"24mm","resolution":"4896 x 3672","cameraMake":"SONY","isoEquivalent":400,"flash":"Flash did not fire","focalLength":"4mm"}},{"image":{"path":"slides\/DSC06052.webp","width":2000,"height":1500},"thumb":{"path":"thumbs\/DSC06052.webp","width":512,"height":410},"thumbCaption":"<span class=\"nr\">38<\/span><div class=\"title\">DSC06052<\/div>","photodata":"<b>Original Date<\/b> <i>5\/17\/20, 4:25\u202FPM<\/i> &middot; <b>Make<\/b> <i>SONY<\/i> &middot; <b>Camera<\/b> <i>DSC-HX90V<\/i> &middot; <b>Lens<\/b> <i>4.1-123mm f\/3.5-6.4<\/i> &middot; <b>Focal Length (35mm)<\/b> <i>24mm<\/i> &middot; <b>Metering Mode<\/b> <i>Multi-segment<\/i> &middot; <b>ISO Equivalent<\/b> <i>400<\/i> &middot; <b>Exposure Time<\/b> <i>1\/250s<\/i> &middot; <b>Aperture<\/b> <i>ƒ\/4.5<\/i> &middot; <b>Exposure bias<\/b> <i>0 EV<\/i> &middot; <b>Exposure Program<\/b> <i>Manual control<\/i> &middot; <b>White balance<\/b> <i>Manual white balance<\/i> &middot; <b>Flash<\/b> <i>Flash did not fire<\/i> &middot; <b>Resolution<\/b> <i>4896 x 3672<\/i>","dates":{"added":1592318088,"dateTaken":1589721942},"fileDate":"2020-05-17T16:25:42.0Z","path":"DSC06052.webp","imageCaption":"<div class=\"title\">DSC06052<\/div>","fileSize":6975973,"name":"DSC06052.webp","comment":"                               ","location":"59.422126,28.117888","category":"image","camera":{"aperture":4.5,"exposureTime":"1\/250s","originalDate":"2020-05-17T16:25:42.0Z","cameraModel":"DSC-HX90V","location":{"altitude":"12.8 metres","latitude":"59° 25' 19.65\"","lat":59.422127,"long":28.117887,"longitude":"28° 7' 4.4\""},"focalLength35mm":"24mm","resolution":"4896 x 3672","cameraMake":"SONY","isoEquivalent":400,"flash":"Flash did not fire","focalLength":"4mm"}},{"image":{"path":"slides\/DSC06053.webp","width":2000,"height":1500},"thumb":{"path":"thumbs\/DSC06053.webp","width":512,"height":410},"thumbCaption":"<span class=\"nr\">39<\/span><div class=\"title\">DSC06053<\/div>","photodata":"<b>Original Date<\/b> <i>5\/17\/20, 4:25\u202FPM<\/i> &middot; <b>Make<\/b> <i>SONY<\/i> &middot; <b>Camera<\/b> <i>DSC-HX90V<\/i> &middot; <b>Lens<\/b> <i>4.1-123mm f\/3.5-6.4<\/i> &middot; <b>Focal Length (35mm)<\/b> <i>24mm<\/i> &middot; <b>Metering Mode<\/b> <i>Multi-segment<\/i> &middot; <b>ISO Equivalent<\/b> <i>400<\/i> &middot; <b>Exposure Time<\/b> <i>1\/250s<\/i> &middot; <b>Aperture<\/b> <i>ƒ\/4.5<\/i> &middot; <b>Exposure bias<\/b> <i>0 EV<\/i> &middot; <b>Exposure Program<\/b> <i>Manual control<\/i> &middot; <b>White balance<\/b> <i>Manual white balance<\/i> &middot; <b>Flash<\/b> <i>Flash did not fire<\/i> &middot; <b>Resolution<\/b> <i>4896 x 3672<\/i>","dates":{"added":1592318088,"dateTaken":1589721948},"fileDate":"2020-05-17T16:25:48.0Z","path":"DSC06053.webp","imageCaption":"<div class=\"title\">DSC06053<\/div>","fileSize":6620305,"name":"DSC06053.webp","comment":"                               ","location":"59.422110,28.117831","category":"image","camera":{"aperture":4.5,"exposureTime":"1\/250s","originalDate":"2020-05-17T16:25:48.0Z","cameraModel":"DSC-HX90V","location":{"altitude":"12.6 metres","latitude":"59° 25' 19.6\"","lat":59.42211,"long":28.11783,"longitude":"28° 7' 4.19\""},"focalLength35mm":"24mm","resolution":"4896 x 3672","cameraMake":"SONY","isoEquivalent":400,"flash":"Flash did not fire","focalLength":"4mm"}},{"image":{"path":"slides\/DSC06054.webp","width":2000,"height":1500},"thumb":{"path":"thumbs\/DSC06054.webp","width":512,"height":410},"thumbCaption":"<span class=\"nr\">40<\/span><div class=\"title\">DSC06054<\/div>","photodata":"<b>Original Date<\/b> <i>5\/17\/20, 4:25\u202FPM<\/i> &middot; <b>Make<\/b> <i>SONY<\/i> &middot; <b>Camera<\/b> <i>DSC-HX90V<\/i> &middot; <b>Lens<\/b> <i>4.1-123mm f\/3.5-6.4<\/i> &middot; <b>Focal Length (35mm)<\/b> <i>24mm<\/i> &middot; <b>Metering Mode<\/b> <i>Multi-segment<\/i> &middot; <b>ISO Equivalent<\/b> <i>400<\/i> &middot; <b>Exposure Time<\/b> <i>1\/250s<\/i> &middot; <b>Aperture<\/b> <i>ƒ\/4.5<\/i> &middot; <b>Exposure bias<\/b> <i>0 EV<\/i> &middot; <b>Exposure Program<\/b> <i>Manual control<\/i> &middot; <b>White balance<\/b> <i>Manual white balance<\/i> &middot; <b>Flash<\/b> <i>Flash did not fire<\/i> &middot; <b>Resolution<\/b> <i>4896 x 3672<\/i>","dates":{"added":1592318088,"dateTaken":1589721953},"fileDate":"2020-05-17T16:25:52.0Z","path":"DSC06054.webp","imageCaption":"<div class=\"title\">DSC06054<\/div>","fileSize":7703323,"name":"DSC06054.webp","comment":"                               ","location":"59.422110,28.117803","category":"image","camera":{"aperture":4.5,"exposureTime":"1\/250s","originalDate":"2020-05-17T16:25:53.0Z","cameraModel":"DSC-HX90V","location":{"altitude":"12.3 metres","latitude":"59° 25' 19.6\"","lat":59.42211,"long":28.117804,"longitude":"28° 7' 4.09\""},"focalLength35mm":"24mm","resolution":"4896 x 3672","cameraMake":"SONY","isoEquivalent":400,"flash":"Flash did not fire","focalLength":"4mm"}},{"image":{"path":"slides\/DSC07774.webp","width":1500,"height":2000},"thumb":{"path":"thumbs\/DSC07774.webp","width":512,"height":410},"thumbCaption":"<span class=\"nr\">41<\/span><div class=\"title\">DSC07774<\/div>","photodata":"<b>Original Date<\/b> <i>5\/26\/17, 5:21\u202FPM<\/i> &middot; <b>Make<\/b> <i>SONY<\/i> &middot; <b>Camera<\/b> <i>DSC-HX90<\/i> &middot; <b>Lens<\/b> <i>4.1-123mm f\/3.5-6.4<\/i> &middot; <b>Focal Length (35mm)<\/b> <i>24mm<\/i> &middot; <b>Metering Mode<\/b> <i>Multi-segment<\/i> &middot; <b>ISO Equivalent<\/b> <i>800<\/i> &middot; <b>Exposure Time<\/b> <i>1\/250s<\/i> &middot; <b>Aperture<\/b> <i>ƒ\/4.5<\/i> &middot; <b>Exposure bias<\/b> <i>0 EV<\/i> &middot; <b>Exposure Program<\/b> <i>Manual control<\/i> &middot; <b>White balance<\/b> <i>Manual white balance<\/i> &middot; <b>Flash<\/b> <i>Flash did not fire<\/i> &middot; <b>Resolution<\/b> <i>3672 x 4896<\/i>","dates":{"added":1505074921,"dateTaken":1495808516},"fileDate":"2017-05-26T17:21:56.0Z","path":"DSC07774.webp","imageCaption":"<div class=\"title\">DSC07774<\/div>","fileSize":2576634,"name":"DSC07774.webp","comment":"                               ","category":"image","camera":{"aperture":4.5,"exposureTime":"1\/250s","originalDate":"2017-05-26T17:21:56.0Z","cameraModel":"DSC-HX90","focalLength35mm":"24mm","resolution":"3672 x 4896","cameraMake":"SONY","isoEquivalent":800,"flash":"Flash did not fire","focalLength":"4mm"}},{"image":{"path":"slides\/DSC07776.webp","width":2000,"height":1500},"thumb":{"path":"thumbs\/DSC07776.webp","width":512,"height":410},"thumbCaption":"<span class=\"nr\">42<\/span><div class=\"title\">DSC07776<\/div>","photodata":"<b>Original Date<\/b> <i>5\/26\/17, 5:22\u202FPM<\/i> &middot; <b>Make<\/b> <i>SONY<\/i> &middot; <b>Camera<\/b> <i>DSC-HX90<\/i> &middot; <b>Lens<\/b> <i>4.1-123mm f\/3.5-6.4<\/i> &middot; <b>Focal Length (35mm)<\/b> <i>24mm<\/i> &middot; <b>Metering Mode<\/b> <i>Multi-segment<\/i> &middot; <b>ISO Equivalent<\/b> <i>400<\/i> &middot; <b>Exposure Time<\/b> <i>1\/250s<\/i> &middot; <b>Aperture<\/b> <i>ƒ\/4.5<\/i> &middot; <b>Exposure bias<\/b> <i>0 EV<\/i> &middot; <b>Exposure Program<\/b> <i>Manual control<\/i> &middot; <b>White balance<\/b> <i>Manual white balance<\/i> &middot; <b>Flash<\/b> <i>Flash did not fire<\/i> &middot; <b>Resolution<\/b> <i>4896 x 3672<\/i>","dates":{"added":1505074921,"dateTaken":1495808531},"fileDate":"2017-05-30T18:59:08.0Z","path":"DSC07776.webp","imageCaption":"<div class=\"title\">DSC07776<\/div>","fileSize":2442208,"name":"DSC07776.webp","comment":"                               ","category":"image","camera":{"aperture":4.5,"exposureTime":"1\/250s","originalDate":"2017-05-26T17:22:11.0Z","cameraModel":"DSC-HX90","focalLength35mm":"24mm","resolution":"4896 x 3672","cameraMake":"SONY","isoEquivalent":400,"flash":"Flash did not fire","focalLength":"4mm"}},{"image":{"path":"slides\/DSC07777.webp","width":2000,"height":1500},"thumb":{"path":"thumbs\/DSC07777.webp","width":512,"height":410},"thumbCaption":"<span class=\"nr\">43<\/span><div class=\"title\">DSC07777<\/div>","photodata":"<b>Original Date<\/b> <i>5\/26\/17, 5:22\u202FPM<\/i> &middot; <b>Make<\/b> <i>SONY<\/i> &middot; <b>Camera<\/b> <i>DSC-HX90<\/i> &middot; <b>Lens<\/b> <i>4.1-123mm f\/3.5-6.4<\/i> &middot; <b>Focal Length (35mm)<\/b> <i>24mm<\/i> &middot; <b>Metering Mode<\/b> <i>Multi-segment<\/i> &middot; <b>ISO Equivalent<\/b> <i>800<\/i> &middot; <b>Exposure Time<\/b> <i>1\/250s<\/i> &middot; <b>Aperture<\/b> <i>ƒ\/4.5<\/i> &middot; <b>Exposure bias<\/b> <i>0 EV<\/i> &middot; <b>Exposure Program<\/b> <i>Manual control<\/i> &middot; <b>White balance<\/b> <i>Manual white balance<\/i> &middot; <b>Flash<\/b> <i>Flash did not fire<\/i> &middot; <b>Resolution<\/b> <i>4896 x 3672<\/i>","dates":{"added":1505074921,"dateTaken":1495808541},"fileDate":"2017-05-26T17:22:20.0Z","path":"DSC07777.webp","imageCaption":"<div class=\"title\">DSC07777<\/div>","fileSize":2654926,"name":"DSC07777.webp","comment":"                               ","category":"image","camera":{"aperture":4.5,"exposureTime":"1\/250s","originalDate":"2017-05-26T17:22:21.0Z","cameraModel":"DSC-HX90","focalLength35mm":"24mm","resolution":"4896 x 3672","cameraMake":"SONY","isoEquivalent":800,"flash":"Flash did not fire","focalLength":"4mm"}},{"image":{"path":"slides\/DSC07778.webp","width":1500,"height":2000},"thumb":{"path":"thumbs\/DSC07778.webp","width":512,"height":410},"thumbCaption":"<span class=\"nr\">44<\/span><div class=\"title\">DSC07778<\/div>","photodata":"<b>Original Date<\/b> <i>5\/26\/17, 5:22\u202FPM<\/i> &middot; <b>Make<\/b> <i>SONY<\/i> &middot; <b>Camera<\/b> <i>DSC-HX90<\/i> &middot; <b>Lens<\/b> <i>4.1-123mm f\/3.5-6.4<\/i> &middot; <b>Focal Length (35mm)<\/b> <i>24mm<\/i> &middot; <b>Metering Mode<\/b> <i>Multi-segment<\/i> &middot; <b>ISO Equivalent<\/b> <i>800<\/i> &middot; <b>Exposure Time<\/b> <i>1\/250s<\/i> &middot; <b>Aperture<\/b> <i>ƒ\/4.5<\/i> &middot; <b>Exposure bias<\/b> <i>0 EV<\/i> &middot; <b>Exposure Program<\/b> <i>Manual control<\/i> &middot; <b>White balance<\/b> <i>Manual white balance<\/i> &middot; <b>Flash<\/b> <i>Flash did not fire<\/i> &middot; <b>Resolution<\/b> <i>3672 x 4896<\/i>","dates":{"added":1505074921,"dateTaken":1495808545},"fileDate":"2017-05-26T17:22:26.0Z","path":"DSC07778.webp","imageCaption":"<div class=\"title\">DSC07778<\/div>","fileSize":3201442,"name":"DSC07778.webp","comment":"                               ","category":"image","camera":{"aperture":4.5,"exposureTime":"1\/250s","originalDate":"2017-05-26T17:22:25.0Z","cameraModel":"DSC-HX90","focalLength35mm":"24mm","resolution":"3672 x 4896","cameraMake":"SONY","isoEquivalent":800,"flash":"Flash did not fire","focalLength":"4mm"}},{"image":{"path":"slides\/DSC07780.webp","width":2000,"height":1500},"thumb":{"path":"thumbs\/DSC07780.webp","width":512,"height":410},"thumbCaption":"<span class=\"nr\">45<\/span><div class=\"title\">DSC07780<\/div>","photodata":"<b>Original Date<\/b> <i>5\/26\/17, 5:22\u202FPM<\/i> &middot; <b>Make<\/b> <i>SONY<\/i> &middot; <b>Camera<\/b> <i>DSC-HX90<\/i> &middot; <b>Lens<\/b> <i>4.1-123mm f\/3.5-6.4<\/i> &middot; <b>Focal Length (35mm)<\/b> <i>24mm<\/i> &middot; <b>Metering Mode<\/b> <i>Multi-segment<\/i> &middot; <b>ISO Equivalent<\/b> <i>800<\/i> &middot; <b>Exposure Time<\/b> <i>1\/250s<\/i> &middot; <b>Aperture<\/b> <i>ƒ\/4.5<\/i> &middot; <b>Exposure bias<\/b> <i>0 EV<\/i> &middot; <b>Exposure Program<\/b> <i>Manual control<\/i> &middot; <b>White balance<\/b> <i>Manual white balance<\/i> &middot; <b>Flash<\/b> <i>Flash did not fire<\/i> &middot; <b>Resolution<\/b> <i>4896 x 3672<\/i>","dates":{"added":1505074921,"dateTaken":1495808573},"fileDate":"2017-05-26T17:22:54.0Z","path":"DSC07780.webp","imageCaption":"<div class=\"title\">DSC07780<\/div>","fileSize":3009276,"name":"DSC07780.webp","comment":"                               ","category":"image","camera":{"aperture":4.5,"exposureTime":"1\/250s","originalDate":"2017-05-26T17:22:53.0Z","cameraModel":"DSC-HX90","focalLength35mm":"24mm","resolution":"4896 x 3672","cameraMake":"SONY","isoEquivalent":800,"flash":"Flash did not fire","focalLength":"4mm"}},{"image":{"path":"slides\/DSC07781.webp","width":2000,"height":1500},"thumb":{"path":"thumbs\/DSC07781.webp","width":512,"height":410},"thumbCaption":"<span class=\"nr\">46<\/span><div class=\"title\">DSC07781<\/div>","photodata":"<b>Original Date<\/b> <i>5\/26\/17, 5:23\u202FPM<\/i> &middot; <b>Make<\/b> <i>SONY<\/i> &middot; <b>Camera<\/b> <i>DSC-HX90<\/i> &middot; <b>Lens<\/b> <i>4.1-123mm f\/3.5-6.4<\/i> &middot; <b>Focal Length (35mm)<\/b> <i>24mm<\/i> &middot; <b>Metering Mode<\/b> <i>Multi-segment<\/i> &middot; <b>ISO Equivalent<\/b> <i>800<\/i> &middot; <b>Exposure Time<\/b> <i>1\/250s<\/i> &middot; <b>Aperture<\/b> <i>ƒ\/4.5<\/i> &middot; <b>Exposure bias<\/b> <i>0 EV<\/i> &middot; <b>Exposure Program<\/b> <i>Manual control<\/i> &middot; <b>White balance<\/b> <i>Manual white balance<\/i> &middot; <b>Flash<\/b> <i>Flash did not fire<\/i> &middot; <b>Resolution<\/b> <i>4896 x 3672<\/i>","dates":{"added":1505074921,"dateTaken":1495808581},"fileDate":"2017-05-26T17:23:02.0Z","path":"DSC07781.webp","imageCaption":"<div class=\"title\">DSC07781<\/div>","fileSize":2471411,"name":"DSC07781.webp","comment":"                               ","category":"image","camera":{"aperture":4.5,"exposureTime":"1\/250s","originalDate":"2017-05-26T17:23:01.0Z","cameraModel":"DSC-HX90","focalLength35mm":"24mm","resolution":"4896 x 3672","cameraMake":"SONY","isoEquivalent":800,"flash":"Flash did not fire","focalLength":"4mm"}},{"image":{"path":"slides\/DSC07799.webp","width":1024,"height":768},"thumb":{"path":"thumbs\/DSC07799.webp","width":512,"height":410},"thumbCaption":"<span class=\"nr\">47<\/span><div class=\"title\">DSC07799<\/div>","photodata":"<b>Original Date<\/b> <i>5\/20\/11, 4:23\u202FPM<\/i> &middot; <b>Make<\/b> <i>SONY<\/i> &middot; <b>Camera<\/b> <i>DSC-T30<\/i> &middot; <b>Focal Length (35mm)<\/b> <i>38mm<\/i> &middot; <b>Metering Mode<\/b> <i>Multi-segment<\/i> &middot; <b>ISO Equivalent<\/b> <i>125<\/i> &middot; <b>Exposure Time<\/b> <i>1\/200s<\/i> &middot; <b>Aperture<\/b> <i>ƒ\/5.6<\/i> &middot; <b>Exposure bias<\/b> <i>0 EV<\/i> &middot; <b>Exposure Program<\/b> <i>Program normal<\/i> &middot; <b>White balance<\/b> <i>Auto white balance<\/i> &middot; <b>Flash<\/b> <i>Flash did not fire<\/i> &middot; <b>Resolution<\/b> <i>2048 x 1536<\/i>","dates":{"added":1505074921,"dateTaken":1305897802},"fileDate":"2014-03-15T20:36:46.0Z","path":"DSC07799.webp","imageCaption":"<div class=\"title\">DSC07799<\/div>","fileSize":508040,"name":"DSC07799.webp","comment":"                               ","category":"image","camera":{"aperture":5.6,"exposureTime":"1\/200s","originalDate":"2011-05-20T16:23:22.0Z","cameraModel":"DSC-T30","focalLength35mm":"38mm","resolution":"2048 x 1536","cameraMake":"SONY","isoEquivalent":125,"flash":"Flash did not fire","focalLength":"6mm"}},{"image":{"path":"slides\/DSC07888.webp","width":2000,"height":1500},"thumb":{"path":"thumbs\/DSC07888.webp","width":512,"height":410},"thumbCaption":"<span class=\"nr\">48<\/span><div class=\"title\">DSC07888<\/div>","photodata":"<b>Original Date<\/b> <i>5\/31\/17, 4:37\u202FPM<\/i> &middot; <b>Make<\/b> <i>SONY<\/i> &middot; <b>Camera<\/b> <i>DSC-HX90<\/i> &middot; <b>Lens<\/b> <i>4.1-123mm f\/3.5-6.4<\/i> &middot; <b>Focal Length (35mm)<\/b> <i>24mm<\/i> &middot; <b>Metering Mode<\/b> <i>Multi-segment<\/i> &middot; <b>ISO Equivalent<\/b> <i>80<\/i> &middot; <b>Exposure Time<\/b> <i>1\/500s<\/i> &middot; <b>Aperture<\/b> <i>ƒ\/4<\/i> &middot; <b>Exposure bias<\/b> <i>0 EV<\/i> &middot; <b>Exposure Program<\/b> <i>Manual control<\/i> &middot; <b>White balance<\/b> <i>Manual white balance<\/i> &middot; <b>Flash<\/b> <i>Flash did not fire<\/i> &middot; <b>Resolution<\/b> <i>4896 x 3672<\/i>","dates":{"added":1505074921,"dateTaken":1496237826},"fileDate":"2017-05-31T16:37:06.0Z","path":"DSC07888.webp","imageCaption":"<div class=\"title\">DSC07888<\/div>","fileSize":2460763,"name":"DSC07888.webp","comment":"                               ","category":"image","camera":{"aperture":4.0,"exposureTime":"1\/500s","originalDate":"2017-05-31T16:37:06.0Z","cameraModel":"DSC-HX90","focalLength35mm":"24mm","resolution":"4896 x 3672","cameraMake":"SONY","isoEquivalent":80,"flash":"Flash did not fire","focalLength":"4mm"}},{"image":{"path":"slides\/DSC07889.webp","width":1500,"height":2000},"thumb":{"path":"thumbs\/DSC07889.webp","width":512,"height":410},"thumbCaption":"<span class=\"nr\">49<\/span><div class=\"title\">DSC07889<\/div>","photodata":"<b>Original Date<\/b> <i>5\/31\/17, 4:37\u202FPM<\/i> &middot; <b>Make<\/b> <i>SONY<\/i> &middot; <b>Camera<\/b> <i>DSC-HX90<\/i> &middot; <b>Lens<\/b> <i>4.1-123mm f\/3.5-6.4<\/i> &middot; <b>Focal Length (35mm)<\/b> <i>24mm<\/i> &middot; <b>Metering Mode<\/b> <i>Multi-segment<\/i> &middot; <b>ISO Equivalent<\/b> <i>80<\/i> &middot; <b>Exposure Time<\/b> <i>1\/500s<\/i> &middot; <b>Aperture<\/b> <i>ƒ\/4.5<\/i> &middot; <b>Exposure bias<\/b> <i>0 EV<\/i> &middot; <b>Exposure Program<\/b> <i>Manual control<\/i> &middot; <b>White balance<\/b> <i>Manual white balance<\/i> &middot; <b>Flash<\/b> <i>Flash did not fire<\/i> &middot; <b>Resolution<\/b> <i>3672 x 4896<\/i>","dates":{"added":1505074921,"dateTaken":1496237837},"fileDate":"2017-05-31T16:37:18.0Z","path":"DSC07889.webp","imageCaption":"<div class=\"title\">DSC07889<\/div>","fileSize":2424725,"name":"DSC07889.webp","comment":"                               ","category":"image","camera":{"aperture":4.5,"exposureTime":"1\/500s","originalDate":"2017-05-31T16:37:17.0Z","cameraModel":"DSC-HX90","focalLength35mm":"24mm","resolution":"3672 x 4896","cameraMake":"SONY","isoEquivalent":80,"flash":"Flash did not fire","focalLength":"4mm"}},{"image":{"path":"slides\/DSC07890.webp","width":2000,"height":1500},"thumb":{"path":"thumbs\/DSC07890.webp","width":512,"height":410},"thumbCaption":"<span class=\"nr\">50<\/span><div class=\"title\">DSC07890<\/div>","photodata":"<b>Original Date<\/b> <i>5\/31\/17, 4:37\u202FPM<\/i> &middot; <b>Make<\/b> <i>SONY<\/i> &middot; <b>Camera<\/b> <i>DSC-HX90<\/i> &middot; <b>Lens<\/b> <i>4.1-123mm f\/3.5-6.4<\/i> &middot; <b>Focal Length (35mm)<\/b> <i>24mm<\/i> &middot; <b>Metering Mode<\/b> <i>Multi-segment<\/i> &middot; <b>ISO Equivalent<\/b> <i>80<\/i> &middot; <b>Exposure Time<\/b> <i>1\/500s<\/i> &middot; <b>Aperture<\/b> <i>ƒ\/4.5<\/i> &middot; <b>Exposure bias<\/b> <i>0 EV<\/i> &middot; <b>Exposure Program<\/b> <i>Manual control<\/i> &middot; <b>White balance<\/b> <i>Manual white balance<\/i> &middot; <b>Flash<\/b> <i>Flash did not fire<\/i> &middot; <b>Resolution<\/b> <i>4896 x 3672<\/i>","dates":{"added":1505074921,"dateTaken":1496237842},"fileDate":"2017-06-04T18:53:30.0Z","path":"DSC07890.webp","imageCaption":"<div class=\"title\">DSC07890<\/div>","fileSize":2546277,"name":"DSC07890.webp","comment":"                               ","category":"image","camera":{"aperture":4.5,"exposureTime":"1\/500s","originalDate":"2017-05-31T16:37:22.0Z","cameraModel":"DSC-HX90","focalLength35mm":"24mm","resolution":"4896 x 3672","cameraMake":"SONY","isoEquivalent":80,"flash":"Flash did not fire","focalLength":"4mm"}},{"path":"IMG_4942.webp","image":{"path":"slides\/IMG_4942.webp","width":1224,"height":1632},"imageCaption":"<div class=\"title\">IMG 4942<\/div>","thumb":{"path":"thumbs\/IMG_4942.webp","width":512,"height":410},"fileSize":1570241,"thumbCaption":"<span class=\"nr\">51<\/span><div class=\"title\">IMG 4942<\/div>","photodata":"<b>Original Date<\/b> <i>5\/21\/14, 4:21\u202FPM<\/i> &middot; <b>Make<\/b> <i>Apple<\/i> &middot; <b>Camera<\/b> <i>iPhone 5<\/i> &middot; <b>Lens Model<\/b> <i>iPhone 5 back camera 4.12mm f\/2.4<\/i> &middot; <b>Focal Length (35mm)<\/b> <i>33mm<\/i> &middot; <b>Metering Mode<\/b> <i>Multi-segment<\/i> &middot; <b>ISO Equivalent<\/b> <i>50<\/i> &middot; <b>Exposure Time<\/b> <i>1\/1391s<\/i> &middot; <b>Aperture<\/b> <i>ƒ\/2.4<\/i> &middot; <b>Exposure Program<\/b> <i>Program normal<\/i> &middot; <b>White balance<\/b> <i>Auto white balance<\/i> &middot; <b>Flash<\/b> <i>Flash did not fire<\/i> &middot; <b>Resolution<\/b> <i>2448 x 3264<\/i>","name":"IMG_4942.webp","dates":{"added":1505074921,"dateTaken":1400678483},"fileDate":"2014-05-21T16:21:24.0Z","category":"image","camera":{"aperture":2.4,"exposureTime":"1\/1391s","originalDate":"2014-05-21T16:21:23.0Z","cameraModel":"iPhone 5","focalLength35mm":"33mm","resolution":"2448 x 3264","cameraMake":"Apple","isoEquivalent":50,"flash":"Flash did not fire","focalLength":"4mm"}},{"path":"IMG_4943.webp","image":{"path":"slides\/IMG_4943.webp","width":1224,"height":1632},"imageCaption":"<div class=\"title\">IMG 4943<\/div>","thumb":{"path":"thumbs\/IMG_4943.webp","width":512,"height":410},"fileSize":1325268,"thumbCaption":"<span class=\"nr\">52<\/span><div class=\"title\">IMG 4943<\/div>","photodata":"<b>Original Date<\/b> <i>5\/21\/14, 4:21\u202FPM<\/i> &middot; <b>Make<\/b> <i>Apple<\/i> &middot; <b>Camera<\/b> <i>iPhone 5<\/i> &middot; <b>Lens Model<\/b> <i>iPhone 5 back camera 4.12mm f\/2.4<\/i> &middot; <b>Focal Length (35mm)<\/b> <i>33mm<\/i> &middot; <b>Metering Mode<\/b> <i>Multi-segment<\/i> &middot; <b>ISO Equivalent<\/b> <i>50<\/i> &middot; <b>Exposure Time<\/b> <i>1\/1938s<\/i> &middot; <b>Aperture<\/b> <i>ƒ\/2.4<\/i> &middot; <b>Exposure Program<\/b> <i>Program normal<\/i> &middot; <b>White balance<\/b> <i>Auto white balance<\/i> &middot; <b>Flash<\/b> <i>Flash did not fire<\/i> &middot; <b>Resolution<\/b> <i>2448 x 3264<\/i>","name":"IMG_4943.webp","dates":{"added":1505074921,"dateTaken":1400678490},"fileDate":"2014-05-21T16:21:30.0Z","category":"image","camera":{"aperture":2.4,"exposureTime":"1\/1938s","originalDate":"2014-05-21T16:21:30.0Z","cameraModel":"iPhone 5","focalLength35mm":"33mm","resolution":"2448 x 3264","cameraMake":"Apple","isoEquivalent":50,"flash":"Flash did not fire","focalLength":"4mm"}},{"path":"IMG_4944.webp","image":{"path":"slides\/IMG_4944.webp","width":1224,"height":1632},"imageCaption":"<div class=\"title\">IMG 4944<\/div>","thumb":{"path":"thumbs\/IMG_4944.webp","width":512,"height":410},"fileSize":1190018,"thumbCaption":"<span class=\"nr\">53<\/span><div class=\"title\">IMG 4944<\/div>","photodata":"<b>Original Date<\/b> <i>5\/21\/14, 4:21\u202FPM<\/i> &middot; <b>Make<\/b> <i>Apple<\/i> &middot; <b>Camera<\/b> <i>iPhone 5<\/i> &middot; <b>Lens Model<\/b> <i>iPhone 5 back camera 4.12mm f\/2.4<\/i> &middot; <b>Focal Length (35mm)<\/b> <i>33mm<\/i> &middot; <b>Metering Mode<\/b> <i>Multi-segment<\/i> &middot; <b>ISO Equivalent<\/b> <i>50<\/i> &middot; <b>Exposure Time<\/b> <i>1\/3012s<\/i> &middot; <b>Aperture<\/b> <i>ƒ\/2.4<\/i> &middot; <b>Exposure Program<\/b> <i>Program normal<\/i> &middot; <b>White balance<\/b> <i>Auto white balance<\/i> &middot; <b>Flash<\/b> <i>Flash did not fire<\/i> &middot; <b>Resolution<\/b> <i>2448 x 3264<\/i>","name":"IMG_4944.webp","dates":{"added":1505074921,"dateTaken":1400678493},"fileDate":"2014-05-21T16:21:36.0Z","category":"image","camera":{"aperture":2.4,"exposureTime":"1\/3012s","originalDate":"2014-05-21T16:21:33.0Z","cameraModel":"iPhone 5","focalLength35mm":"33mm","resolution":"2448 x 3264","cameraMake":"Apple","isoEquivalent":50,"flash":"Flash did not fire","focalLength":"4mm"}},{"path":"IMG_6948.webp","image":{"path":"slides\/IMG_6948.webp","width":1224,"height":1632},"imageCaption":"<div class=\"title\">IMG 6948<\/div>","thumb":{"path":"thumbs\/IMG_6948.webp","width":512,"height":410},"fileSize":1593034,"thumbCaption":"<span class=\"nr\">54<\/span><div class=\"title\">IMG 6948<\/div>","photodata":"<b>Original Date<\/b> <i>8\/30\/14, 7:46\u202FPM<\/i> &middot; <b>Make<\/b> <i>Apple<\/i> &middot; <b>Camera<\/b> <i>iPhone 5<\/i> &middot; <b>Lens Model<\/b> <i>iPhone 5 back camera 4.12mm f\/2.4<\/i> &middot; <b>Focal Length (35mm)<\/b> <i>33mm<\/i> &middot; <b>Metering Mode<\/b> <i>Multi-segment<\/i> &middot; <b>ISO Equivalent<\/b> <i>200<\/i> &middot; <b>Exposure Time<\/b> <i>1\/20s<\/i> &middot; <b>Aperture<\/b> <i>ƒ\/2.4<\/i> &middot; <b>Exposure Program<\/b> <i>Program normal<\/i> &middot; <b>White balance<\/b> <i>Auto white balance<\/i> &middot; <b>Flash<\/b> <i>Flash did not fire<\/i> &middot; <b>Resolution<\/b> <i>2448 x 3264<\/i>","name":"IMG_6948.webp","dates":{"added":1505074921,"dateTaken":1409417207},"fileDate":"2014-08-30T19:46:48.0Z","category":"image","camera":{"aperture":2.4,"exposureTime":"1\/20s","originalDate":"2014-08-30T19:46:47.0Z","cameraModel":"iPhone 5","focalLength35mm":"33mm","resolution":"2448 x 3264","cameraMake":"Apple","isoEquivalent":200,"flash":"Flash did not fire","focalLength":"4mm"}}],"name":"Рябина обыкновенная - Sorbus aucuparia","dates":{"added":1592318088,"dateRange":{"0":1241729174,"1":1589721953}},"fileDate":"2023-01-20T17:53:27.412Z"}