{"path":"%D0%9C%D0%BE%D0%B6%D0%B6%D0%B5%D0%B2%D0%B5%D0%BB%D1%8C%D0%BD%D0%B8%D0%BA%20%D0%BE%D0%B1%D1%8B%D0%BA%D0%BD%D0%BE%D0%B2%D0%B5%D0%BD%D0%BD%D1%8B%D0%B9%20-%20Juniperus%20communis","deepCounters":{"total":23,"images":23,"files":23},"counters":{"total":23,"images":23,"files":23},"thumb":{"path":"thumbs\/DSC00279.webp","width":512,"height":410},"thumbCaption":"<h3>Можжевельник обыкновенный - Juniperus communis<\/h3>","album":{"description":"<br\/>\nPlant anatomy, Hybrids, Pests and Diseases, Carnivorous, Myco-Heterotrophic, Parasitic, Albinos, Fungi, Succulents, Cactuses, Aquatic, Nut-fruited, Tuberous, Ferns, Mosses, Bulbs, Mutants, Witches' brooms, Fairy rings, Prolific petals, Bad luck, Good luck, Colors, Burls, Mycelium, Molds, Journeys.<br\/><br\/>\nTry also other sites: <br\/>\n    <a href=\"https:\/\/herbarium.info\">Herbarium.INFO<\/a>&nbsp;\u2022&nbsp;\n    <a href=\"https:\/\/herbarium.info\/plantarium.info\">Plantarium.INFO<\/a>&nbsp;\u2022&nbsp;\n    <a href=\"https:\/\/fungarium.info\">Fungarium.INFO<\/a>&nbsp;\u2022&nbsp;\n    <a href=\"https:\/\/herbarium.info\/lichenarium.info\">Lichenarium.INFO<\/a>&nbsp;\u2022&nbsp;\n    <a href=\"https:\/\/herbarium.info\/algaerium.info\">Algaerium.INFO<\/a>","title":"Plantarium.INFO"},"objects":[{"image":{"path":"slides\/DSC00279.webp","width":960,"height":1280},"thumb":{"path":"thumbs\/DSC00279.webp","width":512,"height":410},"thumbCaption":"<span class=\"nr\">1<\/span><div class=\"title\">DSC00279<\/div>","photodata":"<b>Original Date<\/b> <i>8\/23\/14, 4:55\u202FPM<\/i> &middot; <b>Make<\/b> <i>SONY<\/i> &middot; <b>Camera<\/b> <i>DSC-HX50<\/i> &middot; <b>Lens<\/b> <i>4.3-129mm f\/3.5-6.3<\/i> &middot; <b>Focal Length<\/b> <i>4.3 mm<\/i> &middot; <b>Metering Mode<\/b> <i>Multi-segment<\/i> &middot; <b>ISO Equivalent<\/b> <i>80<\/i> &middot; <b>Exposure Time<\/b> <i>1\/40s<\/i> &middot; <b>Aperture<\/b> <i>ƒ\/3.5<\/i> &middot; <b>Exposure bias<\/b> <i>0 EV<\/i> &middot; <b>Exposure Program<\/b> <i>Program normal<\/i> &middot; <b>White balance<\/b> <i>Auto white balance<\/i> &middot; <b>Flash<\/b> <i>Flash did not fire<\/i> &middot; <b>Resolution<\/b> <i>1920 x 2560<\/i>","dates":{"added":1408814332,"dateTaken":1408802109},"fileDate":"2014-08-23T18:22:46.0Z","path":"DSC00279.webp","imageCaption":"<div class=\"title\">DSC00279<\/div>","fileSize":583404,"name":"DSC00279.webp","comment":"                               ","category":"image","camera":{"aperture":3.5,"exposureTime":"1\/40s","originalDate":"2014-08-23T16:55:09.0Z","cameraModel":"DSC-HX50","resolution":"1920 x 2560","cameraMake":"SONY","isoEquivalent":80,"flash":"Flash did not fire","focalLength":"4mm"}},{"image":{"path":"slides\/DSC00297.webp","width":960,"height":1280},"thumb":{"path":"thumbs\/DSC00297.webp","width":512,"height":410},"thumbCaption":"<span class=\"nr\">2<\/span><div class=\"title\">DSC00297<\/div>","photodata":"<b>Original Date<\/b> <i>8\/23\/14, 5:06\u202FPM<\/i> &middot; <b>Make<\/b> <i>SONY<\/i> &middot; <b>Camera<\/b> <i>DSC-HX50<\/i> &middot; <b>Lens<\/b> <i>4.3-129mm f\/3.5-6.3<\/i> &middot; <b>Focal Length<\/b> <i>4.3 mm<\/i> &middot; <b>Metering Mode<\/b> <i>Multi-segment<\/i> &middot; <b>ISO Equivalent<\/b> <i>80<\/i> &middot; <b>Exposure Time<\/b> <i>1\/40s<\/i> &middot; <b>Aperture<\/b> <i>ƒ\/3.5<\/i> &middot; <b>Exposure bias<\/b> <i>0 EV<\/i> &middot; <b>Exposure Program<\/b> <i>Program normal<\/i> &middot; <b>White balance<\/b> <i>Auto white balance<\/i> &middot; <b>Flash<\/b> <i>Flash did not fire<\/i> &middot; <b>Resolution<\/b> <i>1920 x 2560<\/i>","dates":{"added":1408814332,"dateTaken":1408802773},"fileDate":"2014-08-23T18:22:44.0Z","path":"DSC00297.webp","imageCaption":"<div class=\"title\">DSC00297<\/div>","fileSize":1058167,"name":"DSC00297.webp","comment":"                               ","category":"image","camera":{"aperture":3.5,"exposureTime":"1\/40s","originalDate":"2014-08-23T17:06:13.0Z","cameraModel":"DSC-HX50","resolution":"1920 x 2560","cameraMake":"SONY","isoEquivalent":80,"flash":"Flash did not fire","focalLength":"4mm"}},{"image":{"path":"slides\/DSC00298.webp","width":960,"height":1280},"thumb":{"path":"thumbs\/DSC00298.webp","width":512,"height":410},"thumbCaption":"<span class=\"nr\">3<\/span><div class=\"title\">DSC00298<\/div>","photodata":"<b>Original Date<\/b> <i>8\/23\/14, 5:06\u202FPM<\/i> &middot; <b>Make<\/b> <i>SONY<\/i> &middot; <b>Camera<\/b> <i>DSC-HX50<\/i> &middot; <b>Lens<\/b> <i>4.3-129mm f\/3.5-6.3<\/i> &middot; <b>Focal Length<\/b> <i>4.3 mm<\/i> &middot; <b>Metering Mode<\/b> <i>Multi-segment<\/i> &middot; <b>ISO Equivalent<\/b> <i>80<\/i> &middot; <b>Exposure Time<\/b> <i>1\/40s<\/i> &middot; <b>Aperture<\/b> <i>ƒ\/3.5<\/i> &middot; <b>Exposure bias<\/b> <i>0 EV<\/i> &middot; <b>Exposure Program<\/b> <i>Program normal<\/i> &middot; <b>White balance<\/b> <i>Auto white balance<\/i> &middot; <b>Flash<\/b> <i>Flash did not fire<\/i> &middot; <b>Resolution<\/b> <i>1920 x 2560<\/i>","dates":{"added":1408814332,"dateTaken":1408802777},"fileDate":"2014-08-23T18:22:44.0Z","path":"DSC00298.webp","imageCaption":"<div class=\"title\">DSC00298<\/div>","fileSize":680862,"name":"DSC00298.webp","comment":"                               ","category":"image","camera":{"aperture":3.5,"exposureTime":"1\/40s","originalDate":"2014-08-23T17:06:17.0Z","cameraModel":"DSC-HX50","resolution":"1920 x 2560","cameraMake":"SONY","isoEquivalent":80,"flash":"Flash did not fire","focalLength":"4mm"}},{"image":{"path":"slides\/DSC02129.webp","width":960,"height":540},"thumb":{"path":"thumbs\/DSC02129.webp","width":512,"height":410},"thumbCaption":"<span class=\"nr\">4<\/span><div class=\"title\">DSC02129<\/div>","photodata":"<b>Original Date<\/b> <i>5\/12\/10, 8:45\u202FAM<\/i> &middot; <b>Make<\/b> <i>SONY<\/i> &middot; <b>Camera<\/b> <i>DSC-T30<\/i> &middot; <b>Focal Length (35mm)<\/b> <i>38mm<\/i> &middot; <b>Metering Mode<\/b> <i>Multi-segment<\/i> &middot; <b>ISO Equivalent<\/b> <i>125<\/i> &middot; <b>Exposure Time<\/b> <i>1\/50s<\/i> &middot; <b>Aperture<\/b> <i>ƒ\/3.5<\/i> &middot; <b>Exposure bias<\/b> <i>0 EV<\/i> &middot; <b>Exposure Program<\/b> <i>Program normal<\/i> &middot; <b>White balance<\/b> <i>Auto white balance<\/i> &middot; <b>Flash<\/b> <i>Flash did not fire<\/i> &middot; <b>Resolution<\/b> <i>1920 x 1080<\/i>","dates":{"added":1396911738,"dateTaken":1273643127},"fileDate":"2014-03-15T20:36:12.0Z","path":"DSC02129.webp","imageCaption":"<div class=\"title\">DSC02129<\/div>","fileSize":808955,"name":"DSC02129.webp","comment":"                               ","category":"image","camera":{"aperture":3.5,"exposureTime":"1\/50s","originalDate":"2010-05-12T08:45:27.0Z","cameraModel":"DSC-T30","focalLength35mm":"38mm","resolution":"1920 x 1080","cameraMake":"SONY","isoEquivalent":125,"flash":"Flash did not fire","focalLength":"6mm"}},{"image":{"path":"slides\/DSC02369.webp","width":1024,"height":768},"thumb":{"path":"thumbs\/DSC02369.webp","width":512,"height":410},"thumbCaption":"<span class=\"nr\">5<\/span><div class=\"title\">DSC02369<\/div>","photodata":"<b>Original Date<\/b> <i>5\/29\/10, 12:56\u202FPM<\/i> &middot; <b>Make<\/b> <i>SONY<\/i> &middot; <b>Camera<\/b> <i>DSC-T30<\/i> &middot; <b>Focal Length (35mm)<\/b> <i>38mm<\/i> &middot; <b>Metering Mode<\/b> <i>Multi-segment<\/i> &middot; <b>ISO Equivalent<\/b> <i>125<\/i> &middot; <b>Exposure Time<\/b> <i>1\/100s<\/i> &middot; <b>Aperture<\/b> <i>ƒ\/3.5<\/i> &middot; <b>Exposure bias<\/b> <i>0 EV<\/i> &middot; <b>Exposure Program<\/b> <i>Program normal<\/i> &middot; <b>White balance<\/b> <i>Auto white balance<\/i> &middot; <b>Flash<\/b> <i>Flash did not fire<\/i> &middot; <b>Resolution<\/b> <i>2048 x 1536<\/i>","dates":{"added":1396911738,"dateTaken":1275126960},"fileDate":"2014-03-15T20:36:12.0Z","path":"DSC02369.webp","imageCaption":"<div class=\"title\">DSC02369<\/div>","fileSize":1321046,"name":"DSC02369.webp","comment":"                               ","category":"image","camera":{"aperture":3.5,"exposureTime":"1\/100s","originalDate":"2010-05-29T12:56:00.0Z","cameraModel":"DSC-T30","focalLength35mm":"38mm","resolution":"2048 x 1536","cameraMake":"SONY","isoEquivalent":125,"flash":"Flash did not fire","focalLength":"6mm"}},{"image":{"path":"slides\/DSC02370.webp","width":1024,"height":768},"thumb":{"path":"thumbs\/DSC02370.webp","width":512,"height":410},"thumbCaption":"<span class=\"nr\">6<\/span><div class=\"title\">DSC02370<\/div>","photodata":"<b>Original Date<\/b> <i>5\/29\/10, 12:56\u202FPM<\/i> &middot; <b>Make<\/b> <i>SONY<\/i> &middot; <b>Camera<\/b> <i>DSC-T30<\/i> &middot; <b>Focal Length (35mm)<\/b> <i>38mm<\/i> &middot; <b>Metering Mode<\/b> <i>Multi-segment<\/i> &middot; <b>ISO Equivalent<\/b> <i>125<\/i> &middot; <b>Exposure Time<\/b> <i>1\/160s<\/i> &middot; <b>Aperture<\/b> <i>ƒ\/3.5<\/i> &middot; <b>Exposure bias<\/b> <i>0 EV<\/i> &middot; <b>Exposure Program<\/b> <i>Program normal<\/i> &middot; <b>White balance<\/b> <i>Auto white balance<\/i> &middot; <b>Flash<\/b> <i>Flash did not fire<\/i> &middot; <b>Resolution<\/b> <i>2048 x 1536<\/i>","dates":{"added":1396911738,"dateTaken":1275126969},"fileDate":"2014-03-15T20:36:12.0Z","path":"DSC02370.webp","imageCaption":"<div class=\"title\">DSC02370<\/div>","fileSize":1133118,"name":"DSC02370.webp","comment":"                               ","category":"image","camera":{"aperture":3.5,"exposureTime":"1\/160s","originalDate":"2010-05-29T12:56:09.0Z","cameraModel":"DSC-T30","focalLength35mm":"38mm","resolution":"2048 x 1536","cameraMake":"SONY","isoEquivalent":125,"flash":"Flash did not fire","focalLength":"6mm"}},{"image":{"path":"slides\/DSC03649.webp","width":960,"height":1280},"thumb":{"path":"thumbs\/DSC03649.webp","width":512,"height":410},"thumbCaption":"<span class=\"nr\">7<\/span><div class=\"title\">DSC03649<\/div>","photodata":"<b>Original Date<\/b> <i>6\/13\/15, 4:43\u202FPM<\/i> &middot; <b>Make<\/b> <i>SONY<\/i> &middot; <b>Camera<\/b> <i>DSC-HX50<\/i> &middot; <b>Lens<\/b> <i>4.3-129mm f\/3.5-6.3<\/i> &middot; <b>Focal Length<\/b> <i>6.9 mm<\/i> &middot; <b>Metering Mode<\/b> <i>Multi-segment<\/i> &middot; <b>ISO Equivalent<\/b> <i>80<\/i> &middot; <b>Exposure Time<\/b> <i>1\/400s<\/i> &middot; <b>Aperture<\/b> <i>ƒ\/4.5<\/i> &middot; <b>Exposure bias<\/b> <i>0 EV<\/i> &middot; <b>Exposure Program<\/b> <i>Landscape mode<\/i> &middot; <b>White balance<\/b> <i>Auto white balance<\/i> &middot; <b>Flash<\/b> <i>Flash did not fire<\/i> &middot; <b>Resolution<\/b> <i>1920 x 2560<\/i>","dates":{"added":1434409468,"dateTaken":1434202998},"fileDate":"2015-06-14T19:04:50.0Z","path":"DSC03649.webp","imageCaption":"<div class=\"title\">DSC03649<\/div>","fileSize":2144938,"name":"DSC03649.webp","comment":"                               ","category":"image","camera":{"aperture":4.5,"exposureTime":"1\/400s","originalDate":"2015-06-13T16:43:18.0Z","cameraModel":"DSC-HX50","resolution":"1920 x 2560","cameraMake":"SONY","isoEquivalent":80,"flash":"Flash did not fire","focalLength":"7mm"}},{"image":{"path":"slides\/DSC03650.webp","width":960,"height":1280},"thumb":{"path":"thumbs\/DSC03650.webp","width":512,"height":410},"thumbCaption":"<span class=\"nr\">8<\/span><div class=\"title\">DSC03650<\/div>","photodata":"<b>Original Date<\/b> <i>6\/13\/15, 4:43\u202FPM<\/i> &middot; <b>Make<\/b> <i>SONY<\/i> &middot; <b>Camera<\/b> <i>DSC-HX50<\/i> &middot; <b>Lens<\/b> <i>4.3-129mm f\/3.5-6.3<\/i> &middot; <b>Focal Length<\/b> <i>6.9 mm<\/i> &middot; <b>Metering Mode<\/b> <i>Multi-segment<\/i> &middot; <b>ISO Equivalent<\/b> <i>80<\/i> &middot; <b>Exposure Time<\/b> <i>1\/320s<\/i> &middot; <b>Aperture<\/b> <i>ƒ\/4.5<\/i> &middot; <b>Exposure bias<\/b> <i>0 EV<\/i> &middot; <b>Exposure Program<\/b> <i>Landscape mode<\/i> &middot; <b>White balance<\/b> <i>Auto white balance<\/i> &middot; <b>Flash<\/b> <i>Flash did not fire<\/i> &middot; <b>Resolution<\/b> <i>1920 x 2560<\/i>","dates":{"added":1434409468,"dateTaken":1434203003},"fileDate":"2015-06-14T19:04:52.0Z","path":"DSC03650.webp","imageCaption":"<div class=\"title\">DSC03650<\/div>","fileSize":2022910,"name":"DSC03650.webp","comment":"                               ","category":"image","camera":{"aperture":4.5,"exposureTime":"1\/320s","originalDate":"2015-06-13T16:43:23.0Z","cameraModel":"DSC-HX50","resolution":"1920 x 2560","cameraMake":"SONY","isoEquivalent":80,"flash":"Flash did not fire","focalLength":"7mm"}},{"image":{"path":"slides\/DSC03651.webp","width":1280,"height":960},"thumb":{"path":"thumbs\/DSC03651.webp","width":512,"height":410},"thumbCaption":"<span class=\"nr\">9<\/span><div class=\"title\">DSC03651<\/div>","photodata":"<b>Original Date<\/b> <i>6\/13\/15, 4:43\u202FPM<\/i> &middot; <b>Make<\/b> <i>SONY<\/i> &middot; <b>Camera<\/b> <i>DSC-HX50<\/i> &middot; <b>Lens<\/b> <i>4.3-129mm f\/3.5-6.3<\/i> &middot; <b>Focal Length<\/b> <i>10.7 mm<\/i> &middot; <b>Metering Mode<\/b> <i>Multi-segment<\/i> &middot; <b>ISO Equivalent<\/b> <i>80<\/i> &middot; <b>Exposure Time<\/b> <i>1\/320s<\/i> &middot; <b>Aperture<\/b> <i>ƒ\/5<\/i> &middot; <b>Exposure bias<\/b> <i>0 EV<\/i> &middot; <b>Exposure Program<\/b> <i>Landscape mode<\/i> &middot; <b>White balance<\/b> <i>Auto white balance<\/i> &middot; <b>Flash<\/b> <i>Flash did not fire<\/i> &middot; <b>Resolution<\/b> <i>2560 x 1920<\/i>","dates":{"added":1434409468,"dateTaken":1434203010},"fileDate":"2015-06-14T19:04:54.0Z","path":"DSC03651.webp","imageCaption":"<div class=\"title\">DSC03651<\/div>","fileSize":1565307,"name":"DSC03651.webp","comment":"                               ","category":"image","camera":{"aperture":5.0,"exposureTime":"1\/320s","originalDate":"2015-06-13T16:43:30.0Z","cameraModel":"DSC-HX50","resolution":"2560 x 1920","cameraMake":"SONY","isoEquivalent":80,"flash":"Flash did not fire","focalLength":"11mm"}},{"image":{"path":"slides\/DSC03652.webp","width":1280,"height":960},"thumb":{"path":"thumbs\/DSC03652.webp","width":512,"height":410},"thumbCaption":"<span class=\"nr\">10<\/span><div class=\"title\">DSC03652<\/div>","photodata":"<b>Original Date<\/b> <i>6\/13\/15, 4:47\u202FPM<\/i> &middot; <b>Make<\/b> <i>SONY<\/i> &middot; <b>Camera<\/b> <i>DSC-HX50<\/i> &middot; <b>Lens<\/b> <i>4.3-129mm f\/3.5-6.3<\/i> &middot; <b>Focal Length<\/b> <i>6.7 mm<\/i> &middot; <b>Metering Mode<\/b> <i>Multi-segment<\/i> &middot; <b>ISO Equivalent<\/b> <i>80<\/i> &middot; <b>Exposure Time<\/b> <i>1\/400s<\/i> &middot; <b>Aperture<\/b> <i>ƒ\/4.5<\/i> &middot; <b>Exposure bias<\/b> <i>0 EV<\/i> &middot; <b>Exposure Program<\/b> <i>Landscape mode<\/i> &middot; <b>White balance<\/b> <i>Auto white balance<\/i> &middot; <b>Flash<\/b> <i>Flash did not fire<\/i> &middot; <b>Resolution<\/b> <i>2560 x 1920<\/i>","dates":{"added":1434409468,"dateTaken":1434203232},"fileDate":"2015-06-14T19:04:56.0Z","path":"DSC03652.webp","imageCaption":"<div class=\"title\">DSC03652<\/div>","fileSize":1476109,"name":"DSC03652.webp","comment":"                               ","category":"image","camera":{"aperture":4.5,"exposureTime":"1\/400s","originalDate":"2015-06-13T16:47:12.0Z","cameraModel":"DSC-HX50","resolution":"2560 x 1920","cameraMake":"SONY","isoEquivalent":80,"flash":"Flash did not fire","focalLength":"7mm"}},{"image":{"path":"slides\/DSC05448.webp","width":960,"height":1280},"thumb":{"path":"thumbs\/DSC05448.webp","width":512,"height":410},"thumbCaption":"<span class=\"nr\">11<\/span><div class=\"title\">DSC05448<\/div>","photodata":"<b>Original Date<\/b> <i>4\/4\/17, 12:22\u202FPM<\/i> &middot; <b>Make<\/b> <i>SONY<\/i> &middot; <b>Camera<\/b> <i>DSC-HX90<\/i> &middot; <b>Lens<\/b> <i>4.1-123mm f\/3.5-6.4<\/i> &middot; <b>Focal Length (35mm)<\/b> <i>24mm<\/i> &middot; <b>Metering Mode<\/b> <i>Spot<\/i> &middot; <b>ISO Equivalent<\/b> <i>80<\/i> &middot; <b>Exposure Time<\/b> <i>1\/400s<\/i> &middot; <b>Aperture<\/b> <i>ƒ\/3.5<\/i> &middot; <b>Exposure bias<\/b> <i>0 EV<\/i> &middot; <b>Exposure Program<\/b> <i>Manual control<\/i> &middot; <b>White balance<\/b> <i>Manual white balance<\/i> &middot; <b>Flash<\/b> <i>Flash did not fire<\/i> &middot; <b>Resolution<\/b> <i>1920 x 2560<\/i>","dates":{"added":1491571057,"dateTaken":1491297774},"fileDate":"2017-04-04T12:22:54.0Z","path":"DSC05448.webp","imageCaption":"<div class=\"title\">DSC05448<\/div>","fileSize":1092951,"name":"DSC05448.webp","comment":"                               ","category":"image","camera":{"aperture":3.5,"exposureTime":"1\/400s","originalDate":"2017-04-04T12:22:54.0Z","cameraModel":"DSC-HX90","focalLength35mm":"24mm","resolution":"1920 x 2560","cameraMake":"SONY","isoEquivalent":80,"flash":"Flash did not fire","focalLength":"4mm"}},{"image":{"path":"slides\/DSC05449.webp","width":960,"height":1280},"thumb":{"path":"thumbs\/DSC05449.webp","width":512,"height":410},"thumbCaption":"<span class=\"nr\">12<\/span><div class=\"title\">DSC05449<\/div>","photodata":"<b>Original Date<\/b> <i>4\/4\/17, 12:23\u202FPM<\/i> &middot; <b>Make<\/b> <i>SONY<\/i> &middot; <b>Camera<\/b> <i>DSC-HX90<\/i> &middot; <b>Lens<\/b> <i>4.1-123mm f\/3.5-6.4<\/i> &middot; <b>Focal Length (35mm)<\/b> <i>24mm<\/i> &middot; <b>Metering Mode<\/b> <i>Spot<\/i> &middot; <b>ISO Equivalent<\/b> <i>80<\/i> &middot; <b>Exposure Time<\/b> <i>1\/400s<\/i> &middot; <b>Aperture<\/b> <i>ƒ\/3.5<\/i> &middot; <b>Exposure bias<\/b> <i>0 EV<\/i> &middot; <b>Exposure Program<\/b> <i>Manual control<\/i> &middot; <b>White balance<\/b> <i>Manual white balance<\/i> &middot; <b>Flash<\/b> <i>Flash did not fire<\/i> &middot; <b>Resolution<\/b> <i>1920 x 2560<\/i>","dates":{"added":1491571057,"dateTaken":1491297782},"fileDate":"2017-04-04T12:23:02.0Z","path":"DSC05449.webp","imageCaption":"<div class=\"title\">DSC05449<\/div>","fileSize":952816,"name":"DSC05449.webp","comment":"                               ","category":"image","camera":{"aperture":3.5,"exposureTime":"1\/400s","originalDate":"2017-04-04T12:23:02.0Z","cameraModel":"DSC-HX90","focalLength35mm":"24mm","resolution":"1920 x 2560","cameraMake":"SONY","isoEquivalent":80,"flash":"Flash did not fire","focalLength":"4mm"}},{"image":{"path":"slides\/DSC05450.webp","width":1280,"height":960},"thumb":{"path":"thumbs\/DSC05450.webp","width":512,"height":410},"thumbCaption":"<span class=\"nr\">13<\/span><div class=\"title\">DSC05450<\/div>","photodata":"<b>Original Date<\/b> <i>4\/4\/17, 12:23\u202FPM<\/i> &middot; <b>Make<\/b> <i>SONY<\/i> &middot; <b>Camera<\/b> <i>DSC-HX90<\/i> &middot; <b>Lens<\/b> <i>4.1-123mm f\/3.5-6.4<\/i> &middot; <b>Focal Length (35mm)<\/b> <i>24mm<\/i> &middot; <b>Metering Mode<\/b> <i>Spot<\/i> &middot; <b>ISO Equivalent<\/b> <i>80<\/i> &middot; <b>Exposure Time<\/b> <i>1\/500s<\/i> &middot; <b>Aperture<\/b> <i>ƒ\/3.5<\/i> &middot; <b>Exposure bias<\/b> <i>0 EV<\/i> &middot; <b>Exposure Program<\/b> <i>Manual control<\/i> &middot; <b>White balance<\/b> <i>Manual white balance<\/i> &middot; <b>Flash<\/b> <i>Flash did not fire<\/i> &middot; <b>Resolution<\/b> <i>2560 x 1920<\/i>","dates":{"added":1491571057,"dateTaken":1491297812},"fileDate":"2017-04-04T12:23:32.0Z","path":"DSC05450.webp","imageCaption":"<div class=\"title\">DSC05450<\/div>","fileSize":672449,"name":"DSC05450.webp","comment":"                               ","category":"image","camera":{"aperture":3.5,"exposureTime":"1\/500s","originalDate":"2017-04-04T12:23:32.0Z","cameraModel":"DSC-HX90","focalLength35mm":"24mm","resolution":"2560 x 1920","cameraMake":"SONY","isoEquivalent":80,"flash":"Flash did not fire","focalLength":"4mm"}},{"image":{"path":"slides\/DSC05450_.webp","width":969,"height":937},"thumb":{"path":"thumbs\/DSC05450_.webp","width":512,"height":410},"thumbCaption":"<span class=\"nr\">14<\/span><div class=\"title\">DSC05450 <\/div>","photodata":"<b>Original Date<\/b> <i>4\/4\/17, 12:23\u202FPM<\/i> &middot; <b>Make<\/b> <i>SONY<\/i> &middot; <b>Camera<\/b> <i>DSC-HX90<\/i> &middot; <b>Lens<\/b> <i>4.1-123mm f\/3.5-6.4<\/i> &middot; <b>Focal Length (35mm)<\/b> <i>24mm<\/i> &middot; <b>Metering Mode<\/b> <i>Spot<\/i> &middot; <b>ISO Equivalent<\/b> <i>80<\/i> &middot; <b>Exposure Time<\/b> <i>1\/500s<\/i> &middot; <b>Aperture<\/b> <i>ƒ\/3.5<\/i> &middot; <b>Exposure bias<\/b> <i>0 EV<\/i> &middot; <b>Exposure Program<\/b> <i>Manual control<\/i> &middot; <b>White balance<\/b> <i>Manual white balance<\/i> &middot; <b>Flash<\/b> <i>Flash did not fire<\/i> &middot; <b>Resolution<\/b> <i>1939 x 1875<\/i>","dates":{"added":1491571057,"dateTaken":1491297812},"fileDate":"2017-04-06T19:31:24.0Z","path":"DSC05450_.webp","imageCaption":"<div class=\"title\">DSC05450 <\/div>","fileSize":1211248,"name":"DSC05450_.webp","comment":"                               ","category":"image","camera":{"aperture":3.5,"exposureTime":"1\/500s","originalDate":"2017-04-04T12:23:32.0Z","cameraModel":"DSC-HX90","focalLength35mm":"24mm","resolution":"1939 x 1875","cameraMake":"SONY","isoEquivalent":80,"flash":"Flash did not fire","focalLength":"4mm"}},{"image":{"path":"slides\/DSC05451.webp","width":1280,"height":960},"thumb":{"path":"thumbs\/DSC05451.webp","width":512,"height":410},"thumbCaption":"<span class=\"nr\">15<\/span><div class=\"title\">DSC05451<\/div>","photodata":"<b>Original Date<\/b> <i>4\/4\/17, 12:23\u202FPM<\/i> &middot; <b>Make<\/b> <i>SONY<\/i> &middot; <b>Camera<\/b> <i>DSC-HX90<\/i> &middot; <b>Lens<\/b> <i>4.1-123mm f\/3.5-6.4<\/i> &middot; <b>Focal Length (35mm)<\/b> <i>24mm<\/i> &middot; <b>Metering Mode<\/b> <i>Spot<\/i> &middot; <b>ISO Equivalent<\/b> <i>80<\/i> &middot; <b>Exposure Time<\/b> <i>1\/500s<\/i> &middot; <b>Aperture<\/b> <i>ƒ\/3.5<\/i> &middot; <b>Exposure bias<\/b> <i>0 EV<\/i> &middot; <b>Exposure Program<\/b> <i>Manual control<\/i> &middot; <b>White balance<\/b> <i>Manual white balance<\/i> &middot; <b>Flash<\/b> <i>Flash did not fire<\/i> &middot; <b>Resolution<\/b> <i>2560 x 1920<\/i>","dates":{"added":1491571057,"dateTaken":1491297824},"fileDate":"2017-04-04T12:23:46.0Z","path":"DSC05451.webp","imageCaption":"<div class=\"title\">DSC05451<\/div>","fileSize":809503,"name":"DSC05451.webp","comment":"                               ","category":"image","camera":{"aperture":3.5,"exposureTime":"1\/500s","originalDate":"2017-04-04T12:23:44.0Z","cameraModel":"DSC-HX90","focalLength35mm":"24mm","resolution":"2560 x 1920","cameraMake":"SONY","isoEquivalent":80,"flash":"Flash did not fire","focalLength":"4mm"}},{"image":{"path":"slides\/DSC06389.webp","width":1280,"height":960},"thumb":{"path":"thumbs\/DSC06389.webp","width":512,"height":410},"thumbCaption":"<span class=\"nr\">16<\/span><div class=\"title\">DSC06389<\/div>","photodata":"<b>Original Date<\/b> <i>4\/20\/13, 2:25\u202FPM<\/i> &middot; <b>Make<\/b> <i>SONY<\/i> &middot; <b>Camera<\/b> <i>DSC-T30<\/i> &middot; <b>Focal Length (35mm)<\/b> <i>38mm<\/i> &middot; <b>Metering Mode<\/b> <i>Multi-segment<\/i> &middot; <b>ISO Equivalent<\/b> <i>125<\/i> &middot; <b>Exposure Time<\/b> <i>1\/200s<\/i> &middot; <b>Aperture<\/b> <i>ƒ\/3.5<\/i> &middot; <b>Exposure bias<\/b> <i>0 EV<\/i> &middot; <b>Exposure Program<\/b> <i>Program normal<\/i> &middot; <b>White balance<\/b> <i>Auto white balance<\/i> &middot; <b>Flash<\/b> <i>Flash did not fire<\/i> &middot; <b>Resolution<\/b> <i>2560 x 1920<\/i>","dates":{"added":1396911738,"dateTaken":1366457119},"fileDate":"2014-03-15T20:36:12.0Z","path":"DSC06389.webp","imageCaption":"<div class=\"title\">DSC06389<\/div>","fileSize":1028411,"name":"DSC06389.webp","comment":"                               ","category":"image","camera":{"aperture":3.5,"exposureTime":"1\/200s","originalDate":"2013-04-20T14:25:19.0Z","cameraModel":"DSC-T30","focalLength35mm":"38mm","resolution":"2560 x 1920","cameraMake":"SONY","isoEquivalent":125,"flash":"Flash did not fire","focalLength":"6mm"}},{"image":{"path":"slides\/DSC06390.webp","width":1280,"height":960},"thumb":{"path":"thumbs\/DSC06390.webp","width":512,"height":410},"thumbCaption":"<span class=\"nr\">17<\/span><div class=\"title\">DSC06390<\/div>","photodata":"<b>Original Date<\/b> <i>4\/20\/13, 2:25\u202FPM<\/i> &middot; <b>Make<\/b> <i>SONY<\/i> &middot; <b>Camera<\/b> <i>DSC-T30<\/i> &middot; <b>Focal Length (35mm)<\/b> <i>38mm<\/i> &middot; <b>Metering Mode<\/b> <i>Multi-segment<\/i> &middot; <b>ISO Equivalent<\/b> <i>125<\/i> &middot; <b>Exposure Time<\/b> <i>1\/125s<\/i> &middot; <b>Aperture<\/b> <i>ƒ\/5.6<\/i> &middot; <b>Exposure bias<\/b> <i>0 EV<\/i> &middot; <b>Exposure Program<\/b> <i>Program normal<\/i> &middot; <b>White balance<\/b> <i>Auto white balance<\/i> &middot; <b>Flash<\/b> <i>Flash did not fire<\/i> &middot; <b>Resolution<\/b> <i>2560 x 1920<\/i>","dates":{"added":1396911738,"dateTaken":1366457125},"fileDate":"2014-03-15T20:36:12.0Z","path":"DSC06390.webp","imageCaption":"<div class=\"title\">DSC06390<\/div>","fileSize":681330,"name":"DSC06390.webp","comment":"                               ","category":"image","camera":{"aperture":5.6,"exposureTime":"1\/125s","originalDate":"2013-04-20T14:25:25.0Z","cameraModel":"DSC-T30","focalLength35mm":"38mm","resolution":"2560 x 1920","cameraMake":"SONY","isoEquivalent":125,"flash":"Flash did not fire","focalLength":"6mm"}},{"image":{"path":"slides\/DSC06391.webp","width":1280,"height":960},"thumb":{"path":"thumbs\/DSC06391.webp","width":512,"height":410},"thumbCaption":"<span class=\"nr\">18<\/span><div class=\"title\">DSC06391<\/div>","photodata":"<b>Original Date<\/b> <i>4\/20\/13, 2:25\u202FPM<\/i> &middot; <b>Make<\/b> <i>SONY<\/i> &middot; <b>Camera<\/b> <i>DSC-T30<\/i> &middot; <b>Focal Length (35mm)<\/b> <i>38mm<\/i> &middot; <b>Metering Mode<\/b> <i>Multi-segment<\/i> &middot; <b>ISO Equivalent<\/b> <i>125<\/i> &middot; <b>Exposure Time<\/b> <i>1\/160s<\/i> &middot; <b>Aperture<\/b> <i>ƒ\/5.6<\/i> &middot; <b>Exposure bias<\/b> <i>0 EV<\/i> &middot; <b>Exposure Program<\/b> <i>Program normal<\/i> &middot; <b>White balance<\/b> <i>Auto white balance<\/i> &middot; <b>Flash<\/b> <i>Flash did not fire<\/i> &middot; <b>Resolution<\/b> <i>2560 x 1920<\/i>","dates":{"added":1396911738,"dateTaken":1366457129},"fileDate":"2014-03-15T20:36:12.0Z","path":"DSC06391.webp","imageCaption":"<div class=\"title\">DSC06391<\/div>","fileSize":727429,"name":"DSC06391.webp","comment":"                               ","category":"image","camera":{"aperture":5.6,"exposureTime":"1\/160s","originalDate":"2013-04-20T14:25:29.0Z","cameraModel":"DSC-T30","focalLength35mm":"38mm","resolution":"2560 x 1920","cameraMake":"SONY","isoEquivalent":125,"flash":"Flash did not fire","focalLength":"6mm"}},{"image":{"path":"slides\/DSC06392.webp","width":960,"height":1280},"thumb":{"path":"thumbs\/DSC06392.webp","width":512,"height":410},"thumbCaption":"<span class=\"nr\">19<\/span><div class=\"title\">DSC06392<\/div>","photodata":"<b>Original Date<\/b> <i>4\/20\/13, 2:25\u202FPM<\/i> &middot; <b>Make<\/b> <i>SONY<\/i> &middot; <b>Camera<\/b> <i>DSC-T30<\/i> &middot; <b>Focal Length (35mm)<\/b> <i>38mm<\/i> &middot; <b>Metering Mode<\/b> <i>Multi-segment<\/i> &middot; <b>ISO Equivalent<\/b> <i>125<\/i> &middot; <b>Exposure Time<\/b> <i>1\/125s<\/i> &middot; <b>Aperture<\/b> <i>ƒ\/3.5<\/i> &middot; <b>Exposure bias<\/b> <i>0 EV<\/i> &middot; <b>Exposure Program<\/b> <i>Program normal<\/i> &middot; <b>White balance<\/b> <i>Auto white balance<\/i> &middot; <b>Flash<\/b> <i>Flash did not fire<\/i> &middot; <b>Resolution<\/b> <i>1920 x 2560<\/i>","dates":{"added":1396911738,"dateTaken":1366457135},"fileDate":"2014-03-15T20:36:12.0Z","path":"DSC06392.webp","imageCaption":"<div class=\"title\">DSC06392<\/div>","fileSize":1222403,"name":"DSC06392.webp","comment":"                               ","category":"image","camera":{"aperture":3.5,"exposureTime":"1\/125s","originalDate":"2013-04-20T14:25:35.0Z","cameraModel":"DSC-T30","focalLength35mm":"38mm","resolution":"1920 x 2560","cameraMake":"SONY","isoEquivalent":125,"flash":"Flash did not fire","focalLength":"6mm"}},{"image":{"path":"slides\/DSC06393.webp","width":1280,"height":960},"thumb":{"path":"thumbs\/DSC06393.webp","width":512,"height":410},"thumbCaption":"<span class=\"nr\">20<\/span><div class=\"title\">DSC06393<\/div>","photodata":"<b>Original Date<\/b> <i>4\/20\/13, 2:26\u202FPM<\/i> &middot; <b>Make<\/b> <i>SONY<\/i> &middot; <b>Camera<\/b> <i>DSC-T30<\/i> &middot; <b>Focal Length (35mm)<\/b> <i>38mm<\/i> &middot; <b>Metering Mode<\/b> <i>Multi-segment<\/i> &middot; <b>ISO Equivalent<\/b> <i>125<\/i> &middot; <b>Exposure Time<\/b> <i>1\/200s<\/i> &middot; <b>Aperture<\/b> <i>ƒ\/3.5<\/i> &middot; <b>Exposure bias<\/b> <i>0 EV<\/i> &middot; <b>Exposure Program<\/b> <i>Program normal<\/i> &middot; <b>White balance<\/b> <i>Auto white balance<\/i> &middot; <b>Flash<\/b> <i>Flash did not fire<\/i> &middot; <b>Resolution<\/b> <i>2560 x 1920<\/i>","dates":{"added":1396911738,"dateTaken":1366457202},"fileDate":"2014-03-15T20:36:12.0Z","path":"DSC06393.webp","imageCaption":"<div class=\"title\">DSC06393<\/div>","fileSize":1621044,"name":"DSC06393.webp","comment":"                               ","category":"image","camera":{"aperture":3.5,"exposureTime":"1\/200s","originalDate":"2013-04-20T14:26:42.0Z","cameraModel":"DSC-T30","focalLength35mm":"38mm","resolution":"2560 x 1920","cameraMake":"SONY","isoEquivalent":125,"flash":"Flash did not fire","focalLength":"6mm"}},{"image":{"path":"slides\/DSC06394.webp","width":1280,"height":960},"thumb":{"path":"thumbs\/DSC06394.webp","width":512,"height":410},"thumbCaption":"<span class=\"nr\">21<\/span><div class=\"title\">DSC06394<\/div>","photodata":"<b>Original Date<\/b> <i>4\/20\/13, 2:26\u202FPM<\/i> &middot; <b>Make<\/b> <i>SONY<\/i> &middot; <b>Camera<\/b> <i>DSC-T30<\/i> &middot; <b>Focal Length (35mm)<\/b> <i>38mm<\/i> &middot; <b>Metering Mode<\/b> <i>Multi-segment<\/i> &middot; <b>ISO Equivalent<\/b> <i>125<\/i> &middot; <b>Exposure Time<\/b> <i>1\/200s<\/i> &middot; <b>Aperture<\/b> <i>ƒ\/3.5<\/i> &middot; <b>Exposure bias<\/b> <i>0 EV<\/i> &middot; <b>Exposure Program<\/b> <i>Program normal<\/i> &middot; <b>White balance<\/b> <i>Auto white balance<\/i> &middot; <b>Flash<\/b> <i>Flash did not fire<\/i> &middot; <b>Resolution<\/b> <i>2560 x 1920<\/i>","dates":{"added":1396911738,"dateTaken":1366457211},"fileDate":"2014-03-15T20:36:14.0Z","path":"DSC06394.webp","imageCaption":"<div class=\"title\">DSC06394<\/div>","fileSize":1438246,"name":"DSC06394.webp","comment":"                               ","category":"image","camera":{"aperture":3.5,"exposureTime":"1\/200s","originalDate":"2013-04-20T14:26:51.0Z","cameraModel":"DSC-T30","focalLength35mm":"38mm","resolution":"2560 x 1920","cameraMake":"SONY","isoEquivalent":125,"flash":"Flash did not fire","focalLength":"6mm"}},{"path":"DSC06532.webp","image":{"path":"slides\/DSC06532.webp","width":1024,"height":768},"imageCaption":"<div class=\"title\">DSC06532<\/div>","thumb":{"path":"thumbs\/DSC06532.webp","width":512,"height":410},"fileSize":573868,"thumbCaption":"<span class=\"nr\">22<\/span><div class=\"title\">DSC06532<\/div>","name":"DSC06532.webp","dates":{"added":1396911738,"dateTaken":1223233720},"fileDate":"2008-10-05T22:08:40.0Z","category":"image","camera":{"originalDate":"2008-10-05T22:08:40.0Z"}},{"path":"DSC06533.webp","image":{"path":"slides\/DSC06533.webp","width":1024,"height":768},"imageCaption":"<div class=\"title\">DSC06533<\/div>","thumb":{"path":"thumbs\/DSC06533.webp","width":512,"height":410},"fileSize":711168,"thumbCaption":"<span class=\"nr\">23<\/span><div class=\"title\">DSC06533<\/div>","name":"DSC06533.webp","dates":{"added":1396911738,"dateTaken":1235217696},"fileDate":"2009-02-21T14:01:36.0Z","category":"image","camera":{"originalDate":"2009-02-21T14:01:36.0Z"}}],"name":"Можжевельник обыкновенный - Juniperus communis","dates":{"added":1491571057,"dateRange":{"0":1223233720,"1":1491297824}},"fileDate":"2023-01-20T17:52:16.477Z"}